Workbook

Sheet C-Summary
A1: RSU 5 Financial Analysis: Executive Summary
A3: All values are live formulas. To test scenarios, change yellow cells on I- and C-FY28Projection sheets.
A5: PART 1: FY27 (2026-2027) -- Budget Going to Voters
B6: Amount | C6: % of FY26
A7: FY26 Adopted Budget | B7: ='I-Budget'!B32
A8: FY27 Proposed (Superintendent) | B8: ='C-Budget'!B16 | C8: ='C-Budget'!B18
A9: Dollar increase from FY26 | B9: ='C-Budget'!B17
A10: Superintendent's initial request was 10.55% | B10: ='I-FY27Reductions'!B17
A11: Total staff/program reductions already applied | B11: ='C-FY27Scenarios'!B16
A12: of which: T1 teaching positions | B12: ='C-FY27Scenarios'!B13
A13: of which: T2 support positions | B13: ='C-FY27Scenarios'!B14
A14: Board adopts March 25, 2026 | ABM: May 13 | Referendum: June 19
A15: EC mandate and structural changes are NOT in FY27. They are FY28.
A16: Historical: FY26 approved at 6.83% (817-494); FY25 at 6.48%; FY24 at 4.99%.
A18: PART 2: FY28 (2027-2028) -- Baseline (No Structural Action)
A19: FY27 adopted (selected scenario) | B19: ='C-FY28Projection'!B7
A20: + Annual cost growth | B20: ='C-FY28Projection'!B7*'C-FY28Projection'!B15
A21: + EC mandate net cost (midpoint) | B21: ='C-FY28Projection'!B19
A22: FY28 BASELINE (no restructuring) | B22: ='C-FY28Projection'!B23
A23: FY28 baseline increase from FY27 | B23: ='C-FY28Projection'!B24
A25: PART 3: PATH A -- Preserve & Strengthen (FY28)
A26: Consolidate middle grades for efficiency. Preserve all elementary schools. Distribute EC.
A27: Structural Change | B27: Annual Budget Impact | C27: Source Sheet
A28: 1. Consolidate grades 7-8 at FMS (district-wide) | B28: =-'C-MSConsol'!B19 | C28: C-MSConsol: Teacher savings from 7-8 consolidation
A29: 2. Consolidate grade 6 at DCS (district-wide) | B29: =0 | C29: C-MSConsol: Included in net FTE calc above
A30: 3. Extracurricular consolidation savings | B30: =-'C-MSConsol'!B20 | C30: C-MSConsol: Combined athletics/activities
A31: 4. Freeport 6th-grade transportation to DCS | B31: ='I-Assumptions'!B13*'I-Assumptions'!B12 | C31: I-Assumptions: 2 routes x $75K
A32: 5. DCS portable classrooms needed | B32: =0 | C32: Net zero: gains 6th sections, loses 7-8 sections
A33: 6. DCS admin complexity (multi-community 6th) | B33: =0 | C33: Complexity offsets any admin savings
A34: 7. Additional line-item efficiencies (midpoint) | B34: =-AVERAGE('I-Assumptions'!B22,'I-Assumptions'!B23) | C34: I-Assumptions: transport, facilities, attrition
A35: TOTAL PATH A SAVINGS (cross-check) | B35: =-SUM(B28:B34)
A36: Path A: FY28 adjusted budget | B36: =B22+SUM(B28:B34)
A37: Path A: FY28 increase from FY27 | B37: =(B36-'C-FY28Projection'!B7)/'C-FY28Projection'!B7
A38: What does NOT change: PES stays PreK-5. All 3 elementary schools preserved.
A39: EC distributed: SpEd classroom at MSS (64 PreK peers for LRE). Itinerant EC at all schools.
A40: Net FTE reduction: ~2.4 teachers (from MS consolidation only).
A42: PART 4: PATH B -- Scenario 2 / Full Restructuring (FY28)
A43: Close PES as K-5. Pownal K-6 to DCS. All PreK to PES (EC center). District-wide 7-8 at FMS.
A44: Component | B44: Gross Lens | C44: True Efficiency
A45: PES instruction budget eliminated | B45: ='C-FY28Paths'!B18 | C45: --
A46: MS consolidation savings (same as Path A) | B46: =-'C-MSConsol'!B21 | C46: =-'C-MSConsol'!B21
A47: Marginal teacher savings from PES closure | B47: -- | C47: ='C-FY28Paths'!B29
A48: PES admin eliminated / DCS coordination | B48: -- | C48: ='C-FY28Paths'!B30+'C-FY28Paths'!B31
A49: PES support services efficiency | B49: -- | C49: ='C-FY28Paths'!B32
A50: Transport: Pownal K-6 to DCS (3 routes) | B50: ='C-FY28Paths'!B19 | C50: ='C-FY28Paths'!B19
A51: Transport: Freeport PreK to PES (3 routes) | B51: ='C-FY28Paths'!B20 | C51: ='C-FY28Paths'!B20
A52: Transport: Durham PreK to PES (2 routes) | B52: ='C-FY28Paths'!B21 | C52: ='C-FY28Paths'!B21
A53: DCS multi-community coordination | B53: ='C-FY28Paths'!B22 | C53: =-'I-Assumptions'!B20
A54: PES EC conversion (amortized over 10 yrs) | B54: ='C-FY28Paths'!B23 | C54: ='C-FY28Paths'!B23
A55: NET SAVINGS | B55: ='C-FY28Paths'!B24 | C55: ='C-FY28Paths'!B36
A56: Gross lens: treats full PES budget as eliminated. Ignores absorption costs.
A57: True efficiency: tracks actual FTE changes. Pownal students still need teachers at DCS.
A58: Total FTE saved (Scenario 2): ='I-FTE'!B42 vs. Path A: ='C-MSConsol'!B18
A60: PART 5: Side-by-Side Comparison (FY28)
A61: Metric | B61: No Action | C61: Path A | D61: Path B (gross) | E61: Path B (true)
A62: FY28 Budget | B62: ='C-FY28Projection'!B23 | C62: ='C-FY28Projection'!B36 | D62: ='C-FY28Projection'!B37 | E62: ='C-FY28Projection'!B23-'C-FY28Paths'!B36
A63: Increase from FY27 adopted | B63: =(B62-'C-FY28Projection'!B7)/'C-FY28Projection'!B7 | C63: =(C62-'C-FY28Projection'!B7)/'C-FY28Projection'!B7 | D63: =(D62-'C-FY28Projection'!B7)/'C-FY28Projection'!B7 | E63: =(E62-'C-FY28Projection'!B7)/'C-FY28Projection'!B7
A64: Structural savings | B64: -- | C64: ='C-FY28Paths'!B13 | D64: ='C-FY28Paths'!B24 | E64: ='C-FY28Paths'!B36
A65: Net FTE change | B65: 0 | C65: =-'C-MSConsol'!B18 | D65: =-'I-FTE'!B42 | E65: =-'I-FTE'!B42
A66: Marginal FTE beyond Path A | B66: -- | C66: -- | D66: ='I-FTE'!B42-'C-MSConsol'!B18 | E66: =D66
A67: EC mandate cost (in all scenarios) | B67: ='C-FY28Projection'!B19 | C67: ='C-FY28Projection'!B19 | D67: ='C-FY28Projection'!B19 | E67: ='C-FY28Projection'!B19
A68: PES PreK-5 preserved? | B68: Yes | C68: Yes | D68: No | E68: No
A69: Young children in home community? | B69: Yes | C69: Yes | D69: No | E69: No
A70: EC parent opt-out risk | B70: N/A | C70: Low | D70: High | E70: High
A71: Political feasibility | B71: Low | C71: High | D71: Low | E71: Low
A72: Reversible? | B72: -- | C72: Yes | D72: No | E72: No
A74: PART 6: Key Assumptions (adjust on I- sheets to test sensitivity)
A75: Assumption | B75: Current Value | C75: Used In | D75: If Changed...
A76: Cost per FTE | B76: ='I-Assumptions'!B8 | C76: C-MSConsol, C-FY28Paths | D76: Higher = more savings from consolidation
A77: Target class size (7-8) | B77: ='I-Assumptions'!B9 | C77: C-MSConsol | D77: Lower target = fewer FTE saved
A78: Bus route cost/year | B78: ='I-Assumptions'!B12 | C78: C-FY28Paths | D78: Higher = worse for Path B
A79: EC net cost (midpoint) | B79: ='C-ECAnalysis'!D12 | C79: C-FY28Projection | D79: Higher = higher FY28 baseline for all paths
A80: Cost growth rate (selected) | B80: ='C-FY28Projection'!B15 | C80: C-FY28Projection | D80: Higher growth = higher FY28 baseline
A81: PES conversion cost | B81: ='I-Assumptions'!B17 | C81: C-FY28Paths | D81: Higher = worse for Path B
A82: Support services efficiency % | B82: ='I-Assumptions'!B21 | C82: C-FY28Paths Path B | D82: Higher = more savings from PES closure
A84: PART 7: What Does NOT Change Between Paths
A85: EC mandate cost (~$690K/yr net) is identical in all scenarios. It is a state requirement.
A86: FY27 budget is decided independently. Structural changes are FY28.
A87: MS consolidation (7-8 at FMS, 6 at DCS) is common to BOTH Path A and Path B.
A88: Per-student funding formula (EPS/ALM/RLC) is set by the state, not by restructuring.
A89: Debt service ($1.07M) and CTE ($337K) are fixed regardless of school configuration.
A90: The FY28 baseline depends on which FY27 budget passes. See C-FY28Projection.
A92: PART 8: Quantified Risk Analysis (see C-RiskModel for detail)
A93: Risk Factor | B93: Mid-Scenario Impact | C93: Notes
A94: Property value decline (10%, Pownal) | B94: ='C-RiskModel'!C17 | C94: Total value lost; per-home ~$34K [Fn 20]
A95: RSU 5 tax revenue loss (annual) | B95: ='C-RiskModel'!B19 | C95: 58.4% of lost property tax at $15.30/thousand
A96: Enrollment attrition (10%) | B96: ='C-RiskModel'!D32 | C96: ~11 students leave RSU 5; state aid lost annually
A97: One-time transition costs (midpoint) | B97: =AVERAGE('C-RiskModel'!B63,'C-RiskModel'!C63) | C97: Staff, conversion, legal, portables, tech
A98: Total annual risk cost (mid scenario) | B98: ='C-RiskModel'!C76 | C98: Sum of quantified annual risks
A99: PATH B RISK-ADJUSTED NET | B99: ='C-RiskModel'!B78 | C99: True net savings minus quantified risk costs
A100: Break-even period (Path B vs Path A) | B100: ='C-RiskModel'!B86 | C100: If negative margin, one-time costs are NEVER recovered
A101: IRREVERSIBILITY: Rebuilding a K-5 program after closure costs more than was saved.
A102: EC OPT-OUT: At 20% opt-out, per-student EC cost rises; SpEd LRE risk is significant.
A103: MAINE LAW: 20-A MRSA requires public hearings, Board vote, potential referendum. [Fn 28]
A104: PATH A RISKS are primarily political/logistical, NOT financial or irreversible.
A106: PART 9: Pownal Recourse Options (see C-Independence, C-LegalAnalysis)
A107: If RSU 5 Board proceeds with Option 2, Pownal has several legal/strategic options.
A109: Option | B109: Key Metric | C109: Notes
A110: §1512 municipal veto (CONTESTED) | B110: ='C-Independence'!B13 | C110: Annual cost IF §1512 applies (likely does NOT for reconfiguration) [Fn 30][Fn 39]
A111: Full withdrawal + tuition (§1466) | B111: ='C-Independence'!B32 | C111: Annual cost change vs. RSU assessment; gains full control [Fn 32]
...

Sheet C-DOEStaffing
A1: CALC: DOE Staffing Trend Analysis
A3: All values are formulas referencing I-DOEStaffing. Source: Maine DOE [Fn 45]
A5: 1. Ten-Year Total FTE Change by School (2016 to 2026)
A6: School | B6: 2016 FTE | C6: 2026 FTE | D6: Change | E6: % Change
A7: PES (Pownal Elementary) | B7: ='I-DOEStaffing'!B11 | C7: ='I-DOEStaffing'!L11 | D7: =C7-B7 | E7: =D7/B7
A8: DCS (Durham Community) | B8: ='I-DOEStaffing'!B12 | C8: ='I-DOEStaffing'!L12 | D8: =C8-B8 | E8: =D8/B8
A9: MSS (Morse Street) | B9: ='I-DOEStaffing'!B13 | C9: ='I-DOEStaffing'!L13 | D9: =C9-B9 | E9: =D9/B9
A10: MLS (Mast Landing) | B10: ='I-DOEStaffing'!B14 | C10: ='I-DOEStaffing'!L14 | D10: =C10-B10 | E10: =D10/B10
A11: FMS (Freeport Middle) | B11: ='I-DOEStaffing'!B15 | C11: ='I-DOEStaffing'!L15 | D11: =C11-B11 | E11: =D11/B11
A12: FHS (Freeport High) | B12: ='I-DOEStaffing'!B16 | C12: ='I-DOEStaffing'!L16 | D12: =C12-B12 | E12: =D12/B12
A13: District-wide (central) | B13: ='I-DOEStaffing'!B17 | C13: ='I-DOEStaffing'!L17 | D13: =C13-B13 | E13: =D13/B13
A15: GRAND TOTAL | B15: ='I-DOEStaffing'!B18 | C15: ='I-DOEStaffing'!L18 | D15: =C15-B15 | E15: =D15/B15
A17: 2. PES Share of District Total FTE (Trend)
A18: Compares PES's share of total staffing to its share of enrollment (~10.5%).
A19: Year | B19: PES FTE | C19: Grand Total | D19: PES Share
A20: 2016 | B20: ='I-DOEStaffing'!B11 | C20: ='I-DOEStaffing'!B18 | D20: =B20/C20
A21: 2017 | B21: ='I-DOEStaffing'!C11 | C21: ='I-DOEStaffing'!C18 | D21: =B21/C21
A22: 2018 | B22: ='I-DOEStaffing'!D11 | C22: ='I-DOEStaffing'!D18 | D22: =B22/C22
A23: 2019 | B23: ='I-DOEStaffing'!E11 | C23: ='I-DOEStaffing'!E18 | D23: =B23/C23
A24: 2020 | B24: ='I-DOEStaffing'!F11 | C24: ='I-DOEStaffing'!F18 | D24: =B24/C24
A25: 2021 | B25: ='I-DOEStaffing'!G11 | C25: ='I-DOEStaffing'!G18 | D25: =B25/C25
A26: 2022 | B26: ='I-DOEStaffing'!H11 | C26: ='I-DOEStaffing'!H18 | D26: =B26/C26
A27: 2023 | B27: ='I-DOEStaffing'!I11 | C27: ='I-DOEStaffing'!I18 | D27: =B27/C27
A28: 2024 | B28: ='I-DOEStaffing'!J11 | C28: ='I-DOEStaffing'!J18 | D28: =B28/C28
A29: 2025 | B29: ='I-DOEStaffing'!K11 | C29: ='I-DOEStaffing'!K18 | D29: =B29/C29
A30: 2026 | B30: ='I-DOEStaffing'!L11 | C30: ='I-DOEStaffing'!L18 | D30: =B30/C30
A32: PES enrollment share (FY27) | B32: ='I-Enrollment'!F12 | C32: =SUM('I-Enrollment'!F10:'I-Enrollment'!F15) | D32: =B32/C32
A33: STAFFING GAP: PES FTE share vs enrollment share | B33: =D30-D32
A35: 3. Instructional Staff (Teachers + Ed Techs + SpEd): 10-Year Change
A36: Combined Classroom Teacher + Ed Tech (I/II/III) + Special Ed Teacher FTE.
A37: School | B37: 2016 Instr | C37: 2026 Instr | D37: Change | E37: % Change
A38: PES | B38: ='I-DOEStaffing'!B23+'I-DOEStaffing'!B43+'I-DOEStaffing'!B33 | C38: ='I-DOEStaffing'!L23+'I-DOEStaffing'!L43+'I-DOEStaffing'!L33 | D38: =C38-B38 | E38: =D38/B38
A39: DCS | B39: ='I-DOEStaffing'!B24+'I-DOEStaffing'!B44+'I-DOEStaffing'!B34 | C39: ='I-DOEStaffing'!L24+'I-DOEStaffing'!L44+'I-DOEStaffing'!L34 | D39: =C39-B39 | E39: =D39/B39
A40: MSS | B40: ='I-DOEStaffing'!B25+'I-DOEStaffing'!B45+'I-DOEStaffing'!B35 | C40: ='I-DOEStaffing'!L25+'I-DOEStaffing'!L45+'I-DOEStaffing'!L35 | D40: =C40-B40 | E40: =D40/B40
A41: MLS | B41: ='I-DOEStaffing'!B26+'I-DOEStaffing'!B46+'I-DOEStaffing'!B36 | C41: ='I-DOEStaffing'!L26+'I-DOEStaffing'!L46+'I-DOEStaffing'!L36 | D41: =C41-B41 | E41: =D41/B41
A42: FMS | B42: ='I-DOEStaffing'!B27+'I-DOEStaffing'!B47+'I-DOEStaffing'!B37 | C42: ='I-DOEStaffing'!L27+'I-DOEStaffing'!L47+'I-DOEStaffing'!L37 | D42: =C42-B42 | E42: =D42/B42
A43: FHS | B43: ='I-DOEStaffing'!B28+'I-DOEStaffing'!B48+'I-DOEStaffing'!B38 | C43: ='I-DOEStaffing'!L28+'I-DOEStaffing'!L48+'I-DOEStaffing'!L38 | D43: =C43-B43 | E43: =D43/B43
A46: 4. PES Special Education Staffing (Trend)
A47: PES SpEd FTE hit 0.0 in school years 2022-23 and 2023-24.
A48: Year | B48: PES SpEd FTE | C48: District Elem Avg | D48: PES vs Avg
A49: 2016 | B49: ='I-DOEStaffing'!B33 | C49: =AVERAGE('I-DOEStaffing'!B34,'I-DOEStaffing'!B35,'I-DOEStaffing'!B36) | D49: =B49-C49
A50: 2017 | B50: ='I-DOEStaffing'!C33 | C50: =AVERAGE('I-DOEStaffing'!C34,'I-DOEStaffing'!C35,'I-DOEStaffing'!C36) | D50: =B50-C50
A51: 2018 | B51: ='I-DOEStaffing'!D33 | C51: =AVERAGE('I-DOEStaffing'!D34,'I-DOEStaffing'!D35,'I-DOEStaffing'!D36) | D51: =B51-C51
A52: 2019 | B52: ='I-DOEStaffing'!E33 | C52: =AVERAGE('I-DOEStaffing'!E34,'I-DOEStaffing'!E35,'I-DOEStaffing'!E36) | D52: =B52-C52
A53: 2020 | B53: ='I-DOEStaffing'!F33 | C53: =AVERAGE('I-DOEStaffing'!F34,'I-DOEStaffing'!F35,'I-DOEStaffing'!F36) | D53: =B53-C53
A54: 2021 | B54: ='I-DOEStaffing'!G33 | C54: =AVERAGE('I-DOEStaffing'!G34,'I-DOEStaffing'!G35,'I-DOEStaffing'!G36) | D54: =B54-C54
A55: 2022 | B55: ='I-DOEStaffing'!H33 | C55: =AVERAGE('I-DOEStaffing'!H34,'I-DOEStaffing'!H35,'I-DOEStaffing'!H36) | D55: =B55-C55
A56: 2023 | B56: ='I-DOEStaffing'!I33 | C56: =AVERAGE('I-DOEStaffing'!I34,'I-DOEStaffing'!I35,'I-DOEStaffing'!I36) | D56: =B56-C56
A57: 2024 | B57: ='I-DOEStaffing'!J33 | C57: =AVERAGE('I-DOEStaffing'!J34,'I-DOEStaffing'!J35,'I-DOEStaffing'!J36) | D57: =B57-C57
A58: 2025 | B58: ='I-DOEStaffing'!K33 | C58: =AVERAGE('I-DOEStaffing'!K34,'I-DOEStaffing'!K35,'I-DOEStaffing'!K36) | D58: =B58-C58
A59: 2026 | B59: ='I-DOEStaffing'!L33 | C59: =AVERAGE('I-DOEStaffing'!L34,'I-DOEStaffing'!L35,'I-DOEStaffing'!L36) | D59: =B59-C59
A61: 5. Cross-Reference: DOE 2026 vs. I-FTE Proposed FY27
A62: DOE 'Classroom Teacher' includes all certified teaching staff (incl. specialists).
A63: I-FTE counts core classroom teachers only. Difference = specialists, PreK, etc.
A64: School | B64: DOE 2026 Teacher | C64: I-FTE Proposed FY27 | D64: Difference | E64: Notes
A65: PES | B65: ='I-DOEStaffing'!L23 | C65: ='I-FTE'!D10 | D65: =B65-C65 | E65: DOE counts PreK, art, music, PE, specialists as 'Classroom Teacher'
A66: DCS | B66: ='I-DOEStaffing'!L24 | C66: ='I-FTE'!D11 | D66: =B66-C66 | E66: DCS is PreK-8; DOE includes all certified teachers
A69: KEY STAFFING FINDINGS (from DOE data)
A70: 1. PES is the ONLY school with negative 10-year FTE change (-8.0%); others grew +3.9% to +36.5%.
A71: 2. District-wide (central office) FTE grew +34.6% over the same period (+35.9 FTE).
A72: 3. PES instructional staff (teachers+ed techs+sped) declined by ~3.8 FTE while other
A73: elementary schools each gained +8.4 to +15.1 FTE.
A74: 4. PES SpEd teacher FTE hit 0.0 in both 2022-23 and 2023-24 school years.
A75: 5. PES share of district FTE fell from 5.9% (2016) to 3.9% (2025), vs. ~10.5% enrollment share.
A76: 6. The per-student cost premium at PES is NOT from overstaffing -- PES runs leaner than all peers.
A77: 7. Resources have been systematically shifted away from PES while Pownal's tax assessment grew 29.8%.

Sheet C-Equity
A1: CALC: Per-Town Equity Analysis
A3: All values are formula-driven from I-Equity inputs. Shows who pays vs. who consumes.
A5: 1. PER-STUDENT COST BY TOWN (FY27)
A6: Metric | B6: Pownal | C6: Durham | D6: Freeport | E6: RSU Average
A7: Students (attributed) | B7: ='I-Equity'!B24 | C7: ='I-Equity'!C25 | D7: ='I-Equity'!D26 | E7: ='I-Equity'!E27
A8: Local tax assessment (RLC + ALM) | B8: ='I-Equity'!B39 | C8: ='I-Equity'!C39 | D8: ='I-Equity'!D39 | E8: ='I-Equity'!E39
A9: Total funding (local + state aid) | B9: ='I-Equity'!B40 | C9: ='I-Equity'!C40 | D9: ='I-Equity'!D40 | E9: ='I-Equity'!E40
A10: LOCAL TAX PER STUDENT | B10: =B8/B7 | C10: =C8/C7 | D10: =D8/D7 | E10: =E8/E7
A11: TOTAL FUNDING PER STUDENT | B11: =B9/B7 | C11: =C9/C7 | D11: =D9/D7 | E11: =E9/E7
A13: 2A. NET POSITION: ACTUAL CONSUMPTION (from C-Consumption)
A14: Uses actual school-level budgets attributed to each town's students.
A15: PES costs are 100% Pownal. FMS/FHS split by enrollment. System pool by student count.
A16: This is the objective cost picture -- it includes PES's small-school premium.
B17: Pownal | C17: Durham | D17: Freeport
A18: Actual budget consumed (C-Consumption) | B18: ='C-Consumption'!D11 | C18: ='C-Consumption'!D19 | D18: ='C-Consumption'!D29
A19: Total contribution (local + state + shared) | B19: ='C-Revenue'!B14 | C19: ='C-Revenue'!C14 | D19: ='C-Revenue'!D14
A20: NET POSITION (revenue - consumption) | B20: =B19-B18 | C20: =C19-C18 | D20: =D19-D18
A21: Actual cost per student | B21: =B18/B7 | C21: =C18/C7 | D21: =D18/D7
A23: Pownal's deficit is REAL but modest: PES costs more per student due to fixed-cost dilution.
A24: Durham's deficit is larger. Freeport is the only net contributor.
A26: 2B. EQUALIZED ANALYSIS: What if every student cost the same?
A27: Uses RSU-wide average per-student cost. Isolates the TAX BURDEN question from
A28: the SCHOOL EFFICIENCY question. Shows whether each town pays its 'fair share'
A29: assuming equal cost per student. Contrast with 2A above for full picture.
B30: Pownal | C30: Durham | D30: Freeport
A31: RSU 5 average cost per student | B31: =E11 | C31: =E11 | D31: =E11
A32: Equalized consumption (students x avg cost) | B32: =B7*B31 | C32: =C7*C31 | D32: =D7*D31
A33: Total contribution (local + state aid) | B33: =B9 | C33: =C9 | D33: =D9
A34: EQUALIZED NET (consumed - contributed) | B34: =B32-B33 | C34: =C32-C33 | D34: =D32-D33
A35: Equalized net per household | B35: =B34/'I-Equity'!B104 | C35: =C34/'I-Equity'!C104 | D35: =D34/'I-Equity'!D104
A37: COMPARE 2A vs 2B: Pownal's actual deficit (2A) is $267K. But if every student cost
A38: the same, Pownal would be a net contributor (2B). The difference = PES's cost premium.
A39: Both are real. Presenting only one without the other is misleading.
A41: 3. COST-SHARING FORMULA IMPACT
A42: Shows how the 85/15 formula distributes ALM vs. what a pure per-student split would look like.
B43: Pownal | C43: Durham | D43: Freeport
A44: Actual ALM paid | B44: ='I-Equity'!B36 | C44: ='I-Equity'!C36 | D44: ='I-Equity'!D36
A45: ALM if split by enrollment only | B45: =(B44+C44+D44)*B7/(B7+C7+D7) | C45: =(B44+C44+D44)*C7/(B7+C7+D7) | D45: =(B44+C44+D44)*D7/(B7+C7+D7)
A46: FORMULA PENALTY (+) or BENEFIT (-) | B46: =B44-B45 | C46: =C44-C45 | D46: =D44-D45
A47: Formula penalty per household | B47: =B46/'I-Equity'!B104 | C47: =C46/'I-Equity'!C104 | D47: =D46/'I-Equity'!D104
A49: 4. POWNAL ASSESSMENT TREND & TAX IMPACT
B50: Value | C50: Source
A51: FY24 Pownal assessment (audited) | B51: ='I-Equity'!B84 | C51: Pownal Annual Report audit [Fn 43]
A52: FY27 Pownal assessment (proposed) | B52: ='I-Equity'!B87 | C52: Budget Handbook [Fn 3]
A53: 3-year dollar increase (FY24→FY27) | B53: =B52-B51
A54: 3-year percentage increase | B54: =B53/B51
A55: RSU budget growth same period | B55: =('I-Equity'!C87-'I-Equity'!C84)/'I-Equity'!C84 | C55: Pownal's share grew faster than budget
A57: FY27 assessment per household (636 homes) | B57: =B52/'I-Equity'!B104
A58: FY24 assessment per household | B58: =B51/'I-Equity'!B104
A59: Per-household increase (3 years) | B59: =(B52-B51)/'I-Equity'!B104
A61: 5. COMPARATIVE FAIRNESS METRICS
A62: Metric | B62: Pownal | C62: Durham | D62: Freeport
A63: % of RSU budget paid locally | B63: =B8/'I-Equity'!C87 | C63: =C8/'I-Equity'!C87 | D63: =D8/'I-Equity'!C87
A64: % of RSU students | B64: =B7/E7 | C64: =C7/E7 | D64: =D7/E7
A65: DISPARITY: pays ÷ gets (1.0 = fair) | B65: =(B8/'I-Equity'!C87)/(B7/E7) | C65: =(C8/'I-Equity'!C87)/(C7/E7) | D65: =(D8/'I-Equity'!C87)/(D7/E7)
A66: >1.0 = pays more than fair share. <1.0 = pays less than fair share.
A67: Pownal's disparity ratio shows it pays significantly more per student than it should.

Sheet C-Independence
A1: CALC: Pownal Independence Financial Analysis
A3: Four scenarios modeled: §1512 veto cost, full withdrawal, withdrawal+AOS, legal challenge.
A4: All values are formula-driven from I-Withdrawal inputs.
A6: SCENARIO A: §1512 MUNICIPAL VETO (if applicable)
A7: Under §1512, if Pownal votes to keep PES open against Board wishes,
A8: Pownal is liable for 'the amount that would be saved if the school were closed.'
A9: IMPORTANT: §1512 likely does NOT apply to Option 2 (reconfiguration, not closure).
A10: This scenario models the cost ceiling IF §1512 were successfully invoked.
A12: TRUE NET SAVINGS from closing PES (from C-FY28Paths) | B12: ='C-FY28Paths'!B36
A13: §1512 LIABILITY = savings RSU would gain | B13: =IF(B12>0,B12,0)
A14: Per-household cost (636 homes) | B14: =B13/'I-Withdrawal'!B112
A15: The TRUE NET from closing PES is approximately -$161K (a COST, not savings).
A16: If net savings are negative, there is NO amount for Pownal to reimburse under §1512.
A17: Revisited annually: Board must re-vote each year to attempt closure.
A19: SCENARIO B: FULL WITHDRAWAL (K-5 independent, tuition 6-12)
A20: Pownal withdraws from RSU 5 under Title 20-A §1466. Operates PES K-5
A21: independently. Tuitions secondary students (6-12) to Freeport or elsewhere.
A23: PES school-level operating cost | B23: ='I-Withdrawal'!B26
A24: Additional admin costs (superintendent, SpEd, etc.) | B24: ='I-Withdrawal'!B46
A25: GROSS INDEPENDENT BUDGET | B25: =SUM(B23:B24)
A27: Less: State EPS share (current) | B27: =-'I-Withdrawal'!B109
A28: Less: Isolated small school adjustment | B28: =-'I-Withdrawal'!B110
A29: NET LOCAL COST (Pownal taxpayers) | B29: =B25+B27+B28
A31: Current Pownal LOCAL tax (RLC + ALM, for comparison) | B31: ='I-Withdrawal'!B12
A32: CHANGE vs. CURRENT RSU ASSESSMENT | B32: =B29-B31
A33: Percentage increase | B33: =B32/B31
A35: New estimated mil rate (education only) | B35: =B29/'I-Withdrawal'!B111*1000
A36: Current RSU education mil rate | B36: ='I-Withdrawal'!B114
A37: Mil rate change | B37: =B35-B36
A38: Annual cost change per household (636 homes) | B38: =B32/'I-Withdrawal'!B112
A40: SCENARIO C: WITHDRAWAL + AOS (shared services)
A41: Same as Scenario B but with AOS cost sharing for admin functions.
A42: Model: AOS #94 (6 towns, shared superintendent); Bristol/South Bristol ESC.
A44: Gross independent budget (from Scenario B) | B44: =B25
A45: Less: AOS shared services savings | B45: =-'I-Withdrawal'!B57
A46: Less: State EPS + small school adjustment | B46: =B27+B28
A47: NET LOCAL COST (AOS model) | B47: =SUM(B44:B46)
A48: CHANGE vs. CURRENT RSU ASSESSMENT | B48: =B47-B31
A49: New estimated mil rate (AOS model) | B49: =B47/'I-Withdrawal'!B111*1000
A50: Annual cost change per household | B50: =B48/'I-Withdrawal'!B112
A52: SCENARIO D: LEGAL CHALLENGE (§1512 contest)
A53: Cost to challenge the 'reconfiguration vs. closure' framing in court or
A54: via petition to Commissioner of Education. One-time cost, uncertain outcome.
A56: Legal challenge cost (low estimate) | B56: ='I-Withdrawal'!B101
A57: Legal challenge cost (high estimate) | B57: ='I-Withdrawal'!C101
A58: Probability of success (analyst assessment) | B58: 0.35
A59: Assessment: statutory text favors 'reconfiguration' interpretation; MSAD #1 precedent
A60: supports district. Counterarguments exist but are untested. [Fn 30][Fn 39]
A63: SCENARIO E: K-8 PES EXPANSION (tuition 9-12 only)
A64: PES expands from K-5 to K-8. Pownal operates its own middle school.
A65: Only grades 9-12 are tuitioned to Freeport High School (or elsewhere).
A66: Trades higher operating cost for lower tuition spend and more control.
A68: PES school-level operating cost (K-5, current) | B68: ='I-Withdrawal'!B26
A69: Additional cost: grades 6-8 staffing + operations | B69: ='I-Withdrawal'!B139
A70: Admin costs (same as Scenario B excl. tuition & contingency) | B70: ='I-Withdrawal'!B46-'I-Withdrawal'!B41-'I-Withdrawal'!B45
A71: HS tuition (9-12 only) | B71: ='I-Withdrawal'!B141
A72: Contingency (5% of above) | B72: =SUM(B68:B71)*0.05
A73: GROSS K-8 INDEPENDENT BUDGET | B73: =SUM(B68:B72)
A75: Less: State EPS share | B75: =-'I-Withdrawal'!B109
A76: Less: Isolated small school adjustment | B76: =-'I-Withdrawal'!B110
A77: NET LOCAL COST (K-8 model) | B77: =B73+B75+B76
A79: CHANGE vs. CURRENT RSU ASSESSMENT | B79: =B77-B31
A80: Annual cost change per household | B80: =B79/'I-Withdrawal'!B112
A81: Mil rate (K-8 model) | B81: =B77/'I-Withdrawal'!B111*1000
A82: vs. Scenario B (K-5 + full tuition) | B82: =B77-B29
A84: K-8 TRADEOFFS:
A85: PRO: Local control through 8th grade; students stay in Pownal 3 more years.
A86: PRO: Reduces tuition dependency; fewer students at other districts' mercy.
A87: PRO: PES has physical capacity (~180 design, ~150 at K-8).
A88: CON: Small MS cohort (~45) limits course variety -- no French, Latin, band at scale.
A89: CON: MS athletics challenging with 15 students/grade.
A90: CON: Requires DOE approval for expanded grade range.
A91: CON: One-time facility upgrades (science lab, ~$75K) not in annual budget.
A92: NEUTRAL: Net annual cost difference vs Scenario B depends on teacher count.
A94: BREAK-EVEN: ALL SCENARIOS vs. RSU MEMBERSHIP
A95: Compares annual cost of each independence scenario to current RSU local tax.
A97: Current RSU local tax (Pownal) | B97: =B31
A98: Scenario B cost (K-5 + full 6-12 tuition) | B98: =B29
A99: Scenario C cost (K-5 + AOS) | B99: =B47
A100: Scenario E cost (K-8 + HS tuition) | B100: =B77
A101: Savings vs RSU: Scenario B (K-5 + tuition) | B101: =-B32
A102: Savings vs RSU: Scenario C (K-5 + AOS) | B102: =-B48
A103: Savings vs RSU: Scenario E (K-8 + HS tuition) | B103: =-B79
A104: Positive = independence SAVES money vs. current RSU local tax.
A105: Negative = independence costs MORE than current RSU local tax.
A107: 5-YEAR COST PROJECTION (Scenario B)
A108: Assumes 3.5% annual cost growth for both RSU and independent operation.
A110: Year | B110: RSU Assessment (est.) | C110: Independent Cost (est.) | D110: Annual Premium | E110: Cumulative Premium
A111: Year 1 | B111: =B31*1.035 | C111: =B29*1.035 | D111: =C111-B111 | E111: =D111+'I-Withdrawal'!B91
A112: Year 2 | B112: =B111*1.035 | C112: =C111*1.035 | D112: =C112-B112 | E112: =E111+D112
A113: Year 3 | B113: =B112*1.035 | C113: =C112*1.035 | D113: =C113-B113 | E113: =E112+D113
A114: Year 4 | B114: =B113*1.035 | C114: =C113*1.035 | D114: =C114-B114 | E114: =E113+D114
A115: Year 5 | B115: =B114*1.035 | C115: =C114*1.035 | D115: =C115-B115 | E115: =E114+D115
A116: 5-YEAR CUMULATIVE COST OF INDEPENDENCE | B116: =E115
A117: This is the total additional cost over 5 years of operating independently vs. staying in RSU 5.
A118: Includes one-time withdrawal process costs in Year 1.
A119: Does NOT include non-financial benefits: full local control, guaranteed school operation,
A120: community identity preservation, property value protection.

Sheet C-LegalAnalysis
A1: CALC: Legal & Strategic Analysis
A3: Structured assessment of Pownal's legal options. Not formula-heavy;
A4: provides decision framework for qualitative dimensions.
A6: PART 1: RECONFIGURATION vs. CLOSURE -- §1512 APPLICABILITY [Fn 30][Fn 39]
A8: STATUTORY TEXT (Title 20-A §1512(4)):
A9: "...a school closing is any action by the regional school unit board
A10: that has the effect of providing no instruction for any students at that school."
A12: Argument | B12: For §1512 Applying | C12: Against §1512 Applying | D12: Strength
A13: Plain text: 'no instruction for any students' | B13: PES K-5 students lose all instruction at PES | C13: EC/PreK students still receive instruction at the building | D13: AGAINST
A14: 'School' vs. 'building' distinction | B14: PES the K-5 school ceases to exist; EC is a new program | C14: Statute refers to 'at that school' = the physical location | D14: MIXED
A15: Legislative intent of §1512 | B15: Enacted to protect small communities from losing their schools | C15: Legislature could have written 'program' but chose 'instruction' | D15: FOR (spirit)
A16: MSAD #1 precedent (Feb 2026) [Fn 39] | B16: Different district; no court ruling; administrative practice only | C16: Pine St Elem -> PreK-Gr1 treated as reconfiguration, not closure | D16: AGAINST
A17: De facto closure doctrine | B17: Every K-5 student displaced; community loses its school in substance | C17: Courts have not applied this doctrine to Maine §1512 specifically | D17: MIXED
A18: Commissioner of Education ruling | B18: Pownal could petition for ruling; untested question = uncertainty | C18: Commissioner may defer to district's administrative discretion | D18: UNCERTAIN
A20: NET ASSESSMENT: | B20: §1512 likely does NOT block Option 2 as framed.
A21: IMPLICATION: | B21: Withdrawal (§1466) is the more reliable recourse path.
A23: PART 2: RECOURSE OPTION COMPARISON MATRIX
A24: Scale: 1 (worst) to 5 (best) for each dimension.
A26: Option | B26: Legal Strength | C26: Est. Cost | D26: Timeline | E26: Control Gained | F26: Reversibility | G26: Risk | H26: Precedent
A27: §1512 legal challenge | B27: 2 | C27: $25K-$88K | D27: 6-18 months | E27: 2 | F27: 5 | G27: 3 | H27: 2
A28: Full RSU withdrawal (§1466) | B28: 5 | C28: $70K + taxes | D28: 12-24 months | E28: 5 | F28: 3 | G28: 3 | H28: 4
A29: Withdrawal + AOS | B29: 5 | C29: $70K + taxes | D29: 12-24 months | E29: 4 | F29: 3 | G29: 2 | H29: 3
A30: Withdrawal + K-8 PES (Scenario E) | B30: 5 | C30: $70K + taxes | D30: 12-24 months | E30: 5 | F30: 2 | G30: 3 | H30: 2
A31: Advocate ALM formula change (§1481-A) | B31: 3 | C31: $5K-$15K | D31: 6-12 months | E31: 2 | F31: 5 | G31: 1 | H31: 3
A32: Leverage (threaten withdrawal) | B32: 4 | C32: $5K-$50K | D32: 3-6 months | E32: 3 | F32: 5 | G32: 1 | H32: 4
A33: Do nothing / accept | B33: 0 | C33: $0 | D33: N/A | E33: N/A | F33: N/A | G33: N/A | H33: N/A
A35: Legal Strength: 5=clear statutory right, 1=contested/weak
A36: Control: 5=full local autonomy, 1=minimal influence
A37: Risk: 5=low risk, 1=high risk. Reversibility: 5=fully reversible, 1=permanent
A38: Precedent: 5=strong Maine precedent, 1=no precedent
A40: PART 3: PARALLEL PRECEDENTS [Fn 33][Fn 34][Fn 38][Fn 39]
A42: District / Case | B42: Action | C42: Outcome | D42: Similarity to Pownal | E42: Relevance
A43: MSAD #1 / Pine Street (2026) [Fn 39] | B43: Elem -> PreK-Gr1 (reconfiguration) | C43: Treated as admin decision, not §1512 closure | D43: HIGH: same EC mandate, same building repurpose | E43: KEY
A44: SAD 75 / Harpswell (2026) [Fn 38] | B44: Community opposed closure of only school | C44: District abandoned ALL closure options | D44: HIGH: small town, community school identity | E44: HIGH
A45: Freeport / RSU 5 (2014) [Fn 33] | B45: Withdrawal petition, full agreement drafted | C45: Vote failed by 76 votes (2152-2228) | D45: DIRECT: same RSU, same legal framework | E45: KEY
A46: Dayton / RSU 23 (2014) [Fn 35] | B46: Full withdrawal, independent operation | C46: Success; mil rate 18.47->20.85; full control | D46: MODERATE: larger, different region | E46: HIGH
A47: Andover / SAD 44 (2015) [Fn 35] | B47: Full withdrawal, independent K-5 | C47: Success; mil rate 15.6->19.6; ~30 students | D47: HIGH: similar enrollment size | E47: HIGH
A48: Embden / RSU 74 (2025) [Fn 37] | B48: Withdrawal petition filed, $50K authorized | C48: Process ongoing | D48: MODERATE: rural, different region | E48: MODERATE
A50: PART 4: STRATEGIC TIMELINE & DECISION TREE
A52: Date / Window | B52: Action | C52: Prerequisite | D52: Statute
A53: Immediate (Spring 2026) | B53: Gather 10% petition signatures (§1466) | C53: Pownal voter roll from last gubernatorial election | D53: 20-A §1466(1)
A54: Spring 2026 | B54: Town vote: authorize withdrawal committee + $50K | C54: Petition signatures verified | D54: 20-A §1466(2)
A55: Spring 2026 (parallel) | B55: File §1512 challenge with Commissioner | C55: Legal counsel retained; Board has voted on Option 2 | D55: 20-A §1512
A56: Summer-Fall 2026 | B56: Withdrawal committee negotiates agreement with RSU 5 | C56: Committee formed; 90-day negotiation window | D56: 20-A §1466(4)
A57: By November 30, 2026 | B57: Final referendum vote on withdrawal agreement | C57: Agreement approved by Commissioner | D57: 20-A §1466(9)
A58: July 1, 2027 | B58: Withdrawal effective; new Pownal SAU operational | C58: Referendum passed by Nov 30, 2026 | D58: 20-A §1466
A59: Fall 2027 | B59: Pownal operates PES independently; tuitions 6-12 | C59: SAU established, superintendent hired, tuition agreements signed
A61: CRITICAL: The Nov 30 deadline is absolute. Missing it delays withdrawal by one full year.
A62: STRATEGY: Initiate §1512 challenge AND withdrawal petition simultaneously.
A63: If §1512 challenge succeeds -> withdrawal becomes unnecessary leverage.
A64: If §1512 challenge fails -> withdrawal is already underway as backup.
A66: PART 5: RECOMMENDED STRATEGY
A68: PHASE 1 (Immediate): Retain education law counsel. File petition for §1512
A69: ruling with Commissioner. Cost: $15K-$25K. This tests the legal question
A70: and creates public record of Pownal's objection.
A72: PHASE 2 (Concurrent): Begin §1466 withdrawal petition. Collect signatures,
A73: hold town vote to authorize committee and $50K. This is the credible threat.
A74: Even if Pownal doesn't ultimately withdraw, the process forces RSU 5 to
A75: negotiate seriously. Freeport's 2014 attempt (failed by 76 votes) proves
... A85: Option 2 as framed.

Sheet C-RiskModel
A1: CALC: Quantified Risk Analysis
A3: Risks that are NOT captured in the C-FY28Paths savings model.
A4: All values are formula-driven or sourced estimates. Citations in brackets.
A6: 1. PROPERTY VALUE IMPACT (Pownal) [Fn 20][Fn 27]
A7: Research: 5-15% decline in communities losing their school (Duncombe & Yinger 2010;
A8: EdWorkingPapers #22-530, 2022). Applied to Pownal's taxable valuation.
A10: Pownal taxable valuation | B10: ='I-Tax'!B13
A11: Estimated housing units (ACS 2023) [Fn 27] | B11: 636
A12: Median home value (ACS 2023) [Fn 27] | B12: 340000
A13: Total Pownal mil rate | B13: ='I-Tax'!B9
A14: Pownal RSU share of tax | B14: ='I-Tax'!B10
A15: Scenario | B15: Decline % | C15: Total Value Lost | D15: Per-Household Loss | E15: Annual Tax Revenue Lost
A16: Low (5%) | B16: 0.05 | C16: =B10*B16 | D16: =B12*B16 | E16: =C16*B13/1000
A17: Mid (10%) | B17: 0.1 | C17: =B10*B17 | D17: =B12*B17 | E17: =C17*B13/1000
A18: High (15%) | B18: 0.15 | C18: =B10*B18 | D18: =B12*B18 | E18: =C18*B13/1000
A19: RSU 5 share of mid-scenario tax loss | B19: =E17*B14
A20: Note: Tax revenue loss occurs gradually (reassessment cycles). Wealth loss is immediate.
A21: At 10% decline, median Pownal home loses ~$34,000 in value.
A23: 2. ENROLLMENT ATTRITION RISK [Fn 20][Fn 28]
A24: If PES closes, some families may leave RSU 5 (move, homeschool, private).
A25: State aid follows the student: each departure costs RSU 5 ongoing revenue.
A27: Current PES enrollment | B27: ='I-FTE'!C10
A28: Pownal state aid (FY25-26) | B28: ='I-Tax'!E41
A29: State aid per PES student | B29: =B28/B27
A30: Scenario | B30: Attrition % | C30: Students Lost | D30: Annual State Revenue Lost
A31: Low (5%) | B31: 0.05 | C31: =ROUND(B27*B31,0) | D31: =C31*B29
A32: Mid (10%) | B32: 0.1 | C32: =ROUND(B27*B32,0) | D32: =C32*B29
A33: High (20%) | B33: 0.2 | C33: =ROUND(B27*B33,0) | D33: =C33*B29
A34: Cost side does NOT shrink proportionally: fixed costs remain, class sizes are already small.
A35: At 10% attrition: 10-11 students leave, ~$50K/yr in state revenue lost to RSU 5.
A37: 3. EC OPT-OUT RISK (Path B Only)
A38: Under Path B, all PreK goes to PES in Pownal. Freeport/Durham families
A39: may refuse 22+ mile bus ride for 3-year-olds and choose private childcare instead.
A40: District PreK is voluntary -- families cannot be compelled to enroll.
A42: Total district PreK enrollment (all schools) | B42: 128 | C42: MSS 64 + DCS 48 + PES 16
A43: EC gross annual cost | B43: ='C-ECAnalysis'!B6
A44: EC cost per student (baseline) | B44: =B43/B42
A45: Scenario | B45: Opt-Out % | C45: Students Lost | D45: Cost/Remaining Student | E45: SpEd LRE Risk
A46: Low (10%) | B46: 0.1 | C46: =ROUND(B42*B46,0) | D46: =B43/(B42-C46) | E46: Moderate
A47: Mid (20%) | B47: 0.2 | C47: =ROUND(B42*B47,0) | D47: =B43/(B42-C47) | E47: Significant
A48: High (30%) | B48: 0.3 | C48: =ROUND(B42*B48,0) | D48: =B43/(B42-C48) | E48: Severe
A49: LRE = Least Restrictive Environment. SpEd requires peers for inclusion classrooms.
A50: Fewer typical peers = harder to deliver compliant services = potential legal exposure.
A51: EC offsets (CDS transfer, IDEA Part B, EPS PreK subsidy) drop with enrollment.
A53: 4. ONE-TIME TRANSITION COSTS [Fn 28]
A54: Costs incurred during implementation year. Not captured in recurring savings model.
A56: Item | B56: Low Estimate | C56: High Estimate | D56: Notes
A57: Staff transition (unemployment, reassignment) | B57: 60000 | C57: 150000 | D57: 4-6 positions affected; depends on attrition vs. layoff
A58: PES building conversion to EC center | B58: 425000 | C58: 743750 | D58: From I-Assumptions; Ch.124 compliance [Fn 21][Fn 24]
A59: Legal/process costs (hearings, consultants) | B59: 50000 | C59: 200000 | D59: Maine 20-A MRSA requires public process [Fn 28]
A60: DCS portable classrooms (if needed) | B60: 0 | C60: 300000 | D60: Depends on final grade configuration at DCS
A61: Curriculum/technology transfer | B61: 25000 | C61: 75000 | D61: Materials, equipment relocation, IT setup
A62: Community engagement/transition support | B62: 15000 | C62: 50000 | D62: Notification, town meetings, family support
A63: TOTAL ONE-TIME COSTS | B63: =SUM(B57:B62) | C63: =SUM(C57:C62)
A65: 5. RISK-ADJUSTED NET SAVINGS (Path B vs. Path A)
A66: Combines C-FY28Paths true-efficiency savings with quantified annual risk costs.
A68: Path A annual savings (from C-FY28Paths) | B68: ='C-FY28Paths'!B13
A69: Path B true net savings (from C-FY28Paths) | B69: ='C-FY28Paths'!B36
A70: Path B MARGINAL savings beyond Path A | B70: =B69-B68
A72: Annual Risk Factor | B72: Low | C72: Mid | D72: High
A73: Property value tax revenue loss | B73: =E16*B14 | C73: =E17*B14 | D73: =E18*B14
A74: Enrollment attrition revenue loss | B74: =D31 | C74: =D32 | D74: =D33
A75: One-time costs (amortized 5 years) | B75: =B63/5 | C75: =AVERAGE(B63,C63)/5 | D75: =C63/5
A76: TOTAL ANNUAL RISK COST | B76: =SUM(B73:B75) | C76: =SUM(C73:C75) | D76: =SUM(D73:D75)
A78: PATH B RISK-ADJUSTED NET (mid scenario) | B78: =B69-C76
A79: Path A savings (unchanged -- no closure risks) | B79: =B68
A81: 6. BREAK-EVEN ANALYSIS
A82: How long until Path B's one-time costs are recovered by marginal savings (if any)?
A84: Path B marginal annual benefit (true net - Path A) | B84: =B70
A85: One-time costs (midpoint) | B85: =AVERAGE(B63,C63)
A86: Break-even period (years) | B86: =IF(B84>0,B85/B84,"NEVER")
A87: If marginal annual savings are negative, one-time costs are NEVER recovered.
A88: This means Path B is strictly worse than Path A from year one onward.
A91: 7. PATH A RISKS (for balanced analysis)
A92: Path A also carries implementation risks, though substantially lower:
A94: MS consolidation: transport cost for Freeport 6th to DCS | B94: ='I-Assumptions'!B13*'I-Assumptions'!B12 | C94: Already modeled in Path A budget
A95: Community identity: DCS becomes multi-town 6th grade | B95: =0 | C95: No direct $ cost, but political sensitivity
A96: Additional efficiencies depend on Board action | B96: =0 | C96: $325K-$650K range is aspirational, not guaranteed
A97: DCS scheduling complexity with Pownal 6th graders | B97: =0 | C97: Manageable with existing admin
A98: Path A risks are primarily political/logistical, NOT financial or irreversible.
A99: Path A is reversible: if MS consolidation doesn't work, grades can be redistributed.

Sheet C-FY28Projection
A1: CALC: FY28 Budget Projection
A3: Projects from FY27 adopted -> FY28 baseline -> FY28 with structural changes.
A4: FY28 is when EC mandate and any restructuring take effect (2027-2028 school year).
A6: Step 1: FY27 Adopted Budget (select scenario)
A7: SELECTED FY27 ADOPTED >> | B7: ='C-FY27Scenarios'!C20
A8: Change cell B above to test different FY27 outcomes. Default = Proposed.
A9: Conservative: ='C-FY27Scenarios'!B20 | Higher: ='C-FY27Scenarios'!D20
A11: Step 2: Cost Growth Rate (from I-CostGrowth)
A12: 3-year average growth (FY24-FY26) | B12: =AVERAGE('I-CostGrowth'!D15:'I-CostGrowth'!D17)
A13: 5-year average growth (FY22-FY26) | B13: =AVERAGE('I-CostGrowth'!D13:'I-CostGrowth'!D17)
A14: 10-year average growth (FY17-FY26) | B14: =AVERAGE('I-CostGrowth'!D8:'I-CostGrowth'!D17)
A15: SELECTED GROWTH RATE >> | B15: =B12
A16: Change cell B above to test different growth assumptions. Default = 3-year avg.
A18: Step 3: EC Mandate (FY28 new cost)
A19: EC net cost (midpoint) | B19: ='C-ECAnalysis'!D12
A21: Step 4: FY28 Baseline (no structural changes)
A22: FY28 operating (FY27 + cost growth) | B22: =B7*(1+B15)
A23: FY28 BASELINE (operating + EC) | B23: =B22+B19
A24: FY28 increase from FY27 | B24: =(B23-B7)/B7
A26: Sensitivity: FY28 Baseline by FY27 Outcome x Growth Rate
A27: FY27 Scenario | B27: 3-yr Growth | C27: 5-yr Growth | D27: 10-yr Growth
A28: Conservative | B28: ='C-FY27Scenarios'!B20*(1+B12)+B19 | C28: ='C-FY27Scenarios'!B20*(1+B13)+B19 | D28: ='C-FY27Scenarios'!B20*(1+B14)+B19
A29: Proposed | B29: ='C-FY27Scenarios'!C20*(1+B12)+B19 | C29: ='C-FY27Scenarios'!C20*(1+B13)+B19 | D29: ='C-FY27Scenarios'!C20*(1+B14)+B19
A30: Higher | B30: ='C-FY27Scenarios'!D20*(1+B12)+B19 | C30: ='C-FY27Scenarios'!D20*(1+B13)+B19 | D30: ='C-FY27Scenarios'!D20*(1+B14)+B19
A32: FY28 with Structural Changes (savings from C-FY28Paths)
A33: Path A total savings | B33: ='C-FY28Paths'!B13
A34: Path B gross savings | B34: ='C-FY28Paths'!B24
A36: FY28 with Path A | B36: =B23-B33
A37: FY28 with Path B (gross) | B37: =B23-B34
A38: Path A increase from FY27 | B38: =(B36-B7)/B7
A39: Path B increase from FY27 | B39: =(B37-B7)/B7

Sheet C-FY27Scenarios
A1: CALC: FY27 Budget Adoption Scenarios
A3: The FY27 budget goes to voters May/June 2026. Board adopts March 25.
A4: EC mandate costs and structural changes are NOT in FY27. They are FY28 decisions.
A6: FY27 Starting Point
A7: FY26 Adopted Budget | B7: ='I-Budget'!B32
A8: Initial request increase (pre-cut) | B8: ='I-FY27Reductions'!B17
A9: "Maintenance of effort" total (before cuts) | B9: =B7+B8
A10: Maint. of effort % increase | B10: =B8/B7
A12: Reductions Already in Proposed Budget
A13: Tier 1 reductions (staff positions) | B13: =SUM('I-FY27Reductions'!F24:'I-FY27Reductions'!F36)
A14: Tier 2 reductions (support positions) | B14: =SUM('I-FY27Reductions'!F40:'I-FY27Reductions'!F46)
A15: Other reductions (tech, facilities) | B15: =SUM('I-FY27Reductions'!E50:'I-FY27Reductions'!E52)
A16: TOTAL REDUCTIONS | B16: =B13+B14+B15
A18: Three Adoption Scenarios
A19: Metric | B19: Conservative | C19: Proposed | D19: Higher
A20: FY27 Budget Total | B20: =B7*1.05 | C20: ='C-Budget'!B16 | D20: ='C-Budget'!B16-B14
A21: % Increase from FY26 | B21: =(B20-B7)/B7 | C21: =(C20-B7)/B7 | D21: =(D20-B7)/B7
A22: Additional cuts beyond proposed | B22: =B20-C20 | C22: 0 | D22: =D20-C20
A23: Positions cut (T1) | B23: 13+ (T1+T2+more) | C23: 13 (T1 only) | D23: 13 (T1; T2 restored)
A24: T2 support positions | B24: Cut | C24: Cut | D24: Restored
A26: The 'Proposed' column matches the Superintendent's recommendation ($47,357,441).
A27: The 'Conservative' scenario targets 5.0% increase. Board may choose differently.
A28: The 'Higher' scenario restores T2 support positions (ed techs, instructional strategist).

Sheet C-FY28Paths
A1: CALC: FY28 Structural Scenario Comparison
A3: Path A and Path B are FY28 (2027-2028) decisions, not FY27.
A4: Savings are independent of the FY28 baseline; they come from restructuring.
A6: PATH A: Preserve & Strengthen (FY28)
A7: Item | B7: Budget Impact | C7: Source / Notes
A8: MS consolidation teacher savings | B8: =-'C-MSConsol'!B21 | C8: See C-MSConsol sheet
A9: DCS admin change (multi-community K-6) | B9: =0 | C9: Revised to $0: complexity increases (I-Assumptions)
A10: Freeport 6th transportation | B10: ='I-Assumptions'!B13*'I-Assumptions'!B12 | C10: Routes x cost/route from I-Assumptions
A11: DCS portable classrooms | B11: =0 | C11: Sections freed by 7-8 offset 6th additions
A12: Additional efficiencies (midpoint) | B12: =-AVERAGE('I-Assumptions'!B22,'I-Assumptions'!B23) | C12: Midpoint of low/high range from I-Assumptions
A13: TOTAL PATH A SAVINGS | B13: =-SUM(B8:B12)
A15: PATH B: Scenario 2 -- Gross Lens (FY28)
A16: Treats full PES instruction budget as eliminated (traditional closure analysis)
A17: Item | B17: Budget Impact | C17: Source / Notes
A18: PES instruction eliminated (gross) | B18: =-('C-Budget'!D7-'I-Budget'!D14) | C18: PES direct cost minus Art 9 facility (stays regardless)
A19: Transport: Pownal K-6 to DCS | B19: ='I-Assumptions'!B14*'I-Assumptions'!B12 | C19: Routes x cost/route from I-Assumptions
A20: Transport: Freeport PreK to PES | B20: ='I-Assumptions'!B15*'I-Assumptions'!B12 | C20: Specialized EC routes from I-Assumptions
A21: Transport: Durham PreK to PES | B21: ='I-Assumptions'!B16*'I-Assumptions'!B12 | C21: Specialized EC routes from I-Assumptions
A22: DCS multi-community coordination | B22: ='I-Assumptions'!B20 | C22: Analyst estimate from I-Assumptions
A23: PES full EC conversion (amortized) | B23: ='I-Assumptions'!B17*'I-Assumptions'!B18/'I-Assumptions'!B19 | C23: Partial cost x multiplier / years from I-Assumptions
A24: PATH B GROSS SAVINGS | B24: =-B18-SUM(B19:B23)
A26: PATH B: True Efficiency Lens -- Absorption-Adjusted (FY28)
A27: Accounts for the fact that Pownal students still need teachers at receiving schools.
A29: Marginal teacher savings (Scenario 2 total - Path A) | B29: =('I-FTE'!B42-'C-MSConsol'!B18)*'I-Assumptions'!B8 | C29: I-FTE Scenario 2 net FTE - C-MSConsol Path A FTE = marginal
A30: PES administration eliminated | B30: ='I-Budget'!D13 | C30: Full Art 7 PES from I-Budget
A31: DCS coordination cost | B31: =-'I-Assumptions'!B20 | C31: Absorbing Pownal families from I-Assumptions
A32: PES support services (partial efficiency) | B32: ='I-Budget'!D12*'I-Assumptions'!B21 | C32: Art 5 x efficiency % from I-Assumptions
A33: True Efficiency Savings | B33: =SUM(B29:B32)
A34: Minus transport (Path B) | B34: =-SUM(B19:B21)
A35: Minus PES conversion (amortized) | B35: =-B23
A36: TRUE NET SAVINGS FROM CLOSING PES | B36: =B33+B34+B35
A38: FINAL COMPARISON (FY28)
A39: Metric | B39: No Action (FY28) | C39: Path A (FY28) | D39: Path B Gross (FY28)
A40: FY28 Budget | B40: ='C-FY28Projection'!B23 | C40: ='C-FY28Projection'!B23-B13 | D40: ='C-FY28Projection'!B23-B24
A41: Increase from FY27 adopted | B41: =(B40-'C-FY28Projection'!B7)/'C-FY28Projection'!B7 | C41: =(C40-'C-FY28Projection'!B7)/'C-FY28Projection'!B7 | D41: =(D40-'C-FY28Projection'!B7)/'C-FY28Projection'!B7
A42: Savings vs. FY28 Baseline | B42: -- | C42: =B13 | D42: =B24
A43: True Net (absorption-adjusted) | B43: N/A | C43: N/A | D43: =B36

Sheet C-Enrollment
A1: CALC: Enrollment & Town-of-Origin Analysis
A3: All values are formulas referencing I-Enrollment.
A5: Cohort Averages
A6: PES avg K-5 grade size | B6: =AVERAGE('I-Enrollment'!B21:'I-Enrollment'!B26)
A7: DCS avg 7-8 grade size | B7: =AVERAGE('I-Enrollment'!B32,'I-Enrollment'!B33)
A9: Town-of-Origin at Shared Schools
A10: School | B10: Pownal (est.) | C10: Durham (est.) | D10: Freeport (est.)
A11: At FMS | B11: =ROUND(B6,0)*3 | C11: 0 | D11: ='I-Enrollment'!F14-B11
A12: At FHS | B12: =ROUND(B6,0)*4 | C12: =ROUND(B7,0)*4 | D12: ='I-Enrollment'!F15-B12-C12
A14: Total Students by Town
A15: Town | B15: Own Schools | C15: At FMS | D15: At FHS | E15: TOTAL
A16: Pownal | B16: ='I-Enrollment'!F12 | C16: =B11 | D16: =B12 | E16: =SUM(B16:D16)
A17: Durham | B17: ='I-Enrollment'!F13 | C17: 0 | D17: =C12 | E17: =SUM(B17:D17)
A18: Freeport | B18: ='I-Enrollment'!F10+'I-Enrollment'!F11 | C18: =D11 | D18: =D12 | E18: =SUM(B18:D18)
A19: DISTRICT TOTAL | E19: =E16+E17+E18

Sheet C-Budget
A1: CALC: Budget Summary & School Direct Costs
A3: All values are SUM formulas referencing I-Budget input sheet.
A5: School Direct Costs (sum of all articles per school)
A6: School | B6: DCS | C6: MSS | D6: PES | E6: MLS | F6: FMS | G6: FHS
A7: Direct Cost | B7: =SUM('I-Budget'!B9:B14) | C7: =SUM('I-Budget'!C9:C14) | D7: =SUM('I-Budget'!D9:D14) | E7: =SUM('I-Budget'!E9:E14) | F7: =SUM('I-Budget'!F9:F14) | G7: =SUM('I-Budget'!G9:G14)
A8: Per Student | B8: =B7/'I-Enrollment'!F13 | C8: =C7/'I-Enrollment'!F10 | D8: =D7/'I-Enrollment'!F12 | E8: =E7/'I-Enrollment'!F11 | F8: =F7/'I-Enrollment'!F14 | G8: =G7/'I-Enrollment'!F15
A10: System-Wide Pool
A11: System-only articles total | B11: =SUM('I-Budget'!B20:'I-Budget'!B24)
A12: SYS/K8/912/CTRL from school articles | B12: =SUM('I-Budget'!H9:'I-Budget'!H14)+SUM('I-Budget'!I9:'I-Budget'!I14)+SUM('I-Budget'!J9:'I-Budget'!J14)+SUM('I-Budget'!K9:'I-Budget'!K14)
A13: TOTAL SYSTEM-WIDE POOL | B13: =B11+B12
A15: GRAND TOTAL (Articles 1-11) | B15: =B7+C7+D7+E7+F7+G7+B13
A16: FY27 TOTAL OPERATING (+ Adult Ed) | B16: =B15+'I-Budget'!B31
A17: FY27 Increase ($) from FY26 | B17: =B16-'I-Budget'!B32
A18: FY27 Increase (%) | B18: =B17/'I-Budget'!B32

Sheet C-Consumption
A1: CALC: Budget Consumption by Town of Origin
A3: Direct costs -> 100% to town. FMS/FHS -> proportional. System -> by student count.
A5: Pownal Consumption
A6: Component | B6: School Total | C6: Share % | D6: Town's Share
A7: PES (100%) | B7: ='C-Budget'!D7 | C7: =1 | D7: =B7*C7
A8: FMS (Pownal share) | B8: ='C-Budget'!F7 | C8: ='C-Enrollment'!B11/'I-Enrollment'!F14 | D8: =B8*C8
A9: FHS (Pownal share) | B9: ='C-Budget'!G7 | C9: ='C-Enrollment'!B12/'I-Enrollment'!F15 | D9: =B9*C9
A10: System (Pownal share) | B10: ='C-Budget'!B13 | C10: ='C-Enrollment'!E16/'C-Enrollment'!E19 | D10: =B10*C10
A11: Pownal TOTAL | D11: =SUM(D7:D10)
A12: Pownal Per Student | D12: =D11/'C-Enrollment'!E16
A14: Durham Consumption
A15: Component | B15: School Total | C15: Share % | D15: Town's Share
A16: DCS (100%) | B16: ='C-Budget'!B7 | C16: =1 | D16: =B16*C16
A17: FHS (Durham share) | B17: ='C-Budget'!G7 | C17: ='C-Enrollment'!C12/'I-Enrollment'!F15 | D17: =B17*C17
A18: System (Durham share) | B18: ='C-Budget'!B13 | C18: ='C-Enrollment'!E17/'C-Enrollment'!E19 | D18: =B18*C18
A19: Durham TOTAL | D19: =SUM(D16:D18)
A20: Durham Per Student | D20: =D19/'C-Enrollment'!E17
A22: Freeport Consumption
A23: Component | B23: School Total | C23: Share % | D23: Town's Share
A24: MSS (100%) | B24: ='C-Budget'!C7 | C24: =1 | D24: =B24*C24
A25: MLS (100%) | B25: ='C-Budget'!E7 | C25: =1 | D25: =B25*C25
A26: FMS (Freeport share) | B26: ='C-Budget'!F7 | C26: ='C-Enrollment'!D11/'I-Enrollment'!F14 | D26: =B26*C26
A27: FHS (Freeport share) | B27: ='C-Budget'!G7 | C27: ='C-Enrollment'!D12/'I-Enrollment'!F15 | D27: =B27*C27
A28: System (Freeport share) | B28: ='C-Budget'!B13 | C28: ='C-Enrollment'!E18/'C-Enrollment'!E19 | D28: =B28*C28
A29: Freeport TOTAL | D29: =SUM(D24:D28)
A30: Freeport Per Student | D30: =D29/'C-Enrollment'!E18
A33: Integrity Check
A34: Sum of Town Consumption | D34: =D11+D19+D29
A35: Budget Total (should match) | D35: ='C-Budget'!B15
A36: Variance | D36: =D34-D35

Sheet C-Revenue
A1: CALC: Revenue & Net Fiscal Position
A3: All values reference I-Revenue and C-Enrollment.
A5: ALM Percentage (computed)
A6: Pownal ALM % | B6: ='I-Revenue'!B10/('I-Revenue'!B10+'I-Revenue'!C10+'I-Revenue'!D10)
A7: Durham ALM % | B7: ='I-Revenue'!C10/('I-Revenue'!B10+'I-Revenue'!C10+'I-Revenue'!D10)
A8: Freeport ALM % | B8: ='I-Revenue'!D10/('I-Revenue'!B10+'I-Revenue'!C10+'I-Revenue'!D10)
A10: Total Revenue by Town
A11: Component | B11: Pownal | C11: Durham | D11: Freeport
A12: Total Contribution | B12: =SUM('I-Revenue'!B9:'I-Revenue'!B12) | C12: =SUM('I-Revenue'!C9:'I-Revenue'!C12) | D12: =SUM('I-Revenue'!D9:'I-Revenue'!D12)
A13: Shared Revenue | B13: ='I-Revenue'!B14*B6 | C13: ='I-Revenue'!B14*B7 | D13: ='I-Revenue'!B14*B8
A14: TOTAL REVENUE | B14: =B12+B13 | C14: =C12+C13 | D14: =D12+D13
A16: Net Fiscal Position
A17: Town | B17: Revenue | C17: Consumption | D17: Net Position | E17: Students | F17: Rev/Stu | G17: Cost/Stu
A18: Pownal | B18: =B14 | C18: ='C-Consumption'!D11 | D18: =B18-C18 | E18: ='C-Enrollment'!E16 | F18: =B18/E18 | G18: =C18/E18
A19: Durham | B19: =C14 | C19: ='C-Consumption'!D19 | D19: =B19-C19 | E19: ='C-Enrollment'!E17 | F19: =B19/E19 | G19: =C19/E19
A20: Freeport | B20: =D14 | C20: ='C-Consumption'!D29 | D20: =B20-C20 | E20: ='C-Enrollment'!E18 | F20: =B20/E20 | G20: =C20/E20

Sheet C-Tax
A1: CALC: Tax Analysis
A3: All values reference I-Tax and I-Revenue input sheets.
A5: RSU Net Tax Impact (RLC + ALM + Non-Shared Debt)
A6: Pownal | B6: ='I-Revenue'!B9+'I-Revenue'!B10+'I-Revenue'!B12
A7: Durham | B7: ='I-Revenue'!C9+'I-Revenue'!C10+'I-Revenue'!C12
A8: Freeport | B8: ='I-Revenue'!D9+'I-Revenue'!D10+'I-Revenue'!D12
A10: Equalized School Mil Rates
A11: Town | B11: RSU Net Tax | C11: State Val | D11: Eq School Mil | E11: Local Mil | F11: Assessment Ratio
A12: Pownal | B12: =B6 | C12: ='I-Tax'!B14 | D12: =B12/C12*1000 | E12: =B12/'I-Tax'!B13*1000 | F12: ='I-Tax'!B13/'I-Tax'!B14
A13: Durham | B13: =B7 | C13: ='I-Tax'!B35 | D13: =B13/C13*1000 | E13: =B13/'I-Tax'!B34*1000 | F13: ='I-Tax'!B34/'I-Tax'!B35
A14: Freeport | B14: =B8 | C14: ='I-Tax'!B25 | D14: =B14/C14*1000 | E14: =B14/'I-Tax'!B24*1000 | F14: ='I-Tax'!B24/'I-Tax'!B25
A16: Per-Student Tax Burden
A17: Town | B17: RSU Net Tax | C17: Students | D17: Tax/Student
A18: Pownal | B18: =B6 | C18: ='C-Enrollment'!E16 | D18: =B18/C18
A19: Durham | B19: =B7 | C19: ='C-Enrollment'!E17 | D19: =B19/C19
A20: Freeport | B20: =B8 | C20: ='C-Enrollment'!E18 | D20: =B20/C20

Sheet C-CostPremium
A1: CALC: PES Per-Student Cost Premium
A3: Compares PES per-student cost vs average of DCS, MSS, MLS from I-Budget.
A5: Article | B5: PES $/Stu | C5: DCS $/Stu | D5: MSS $/Stu | E5: MLS $/Stu | F5: Other Avg | G5: PES Premium
A6: Art 1 - Regular Instr. | B6: ='I-Budget'!D9/'I-Enrollment'!F12 | C6: ='I-Budget'!B9/'I-Enrollment'!F13 | D6: ='I-Budget'!C9/'I-Enrollment'!F10 | E6: ='I-Budget'!E9/'I-Enrollment'!F11 | F6: =AVERAGE(C6:E6) | G6: =B6-F6
A7: Art 2 - Special Ed | B7: ='I-Budget'!D10/'I-Enrollment'!F12 | C7: ='I-Budget'!B10/'I-Enrollment'!F13 | D7: ='I-Budget'!C10/'I-Enrollment'!F10 | E7: ='I-Budget'!E10/'I-Enrollment'!F11 | F7: =AVERAGE(C7:E7) | G7: =B7-F7
A8: Art 4 - Other Instr. | B8: ='I-Budget'!D11/'I-Enrollment'!F12 | C8: ='I-Budget'!B11/'I-Enrollment'!F13 | D8: ='I-Budget'!C11/'I-Enrollment'!F10 | E8: ='I-Budget'!E11/'I-Enrollment'!F11 | F8: =AVERAGE(C8:E8) | G8: =B8-F8
A9: Art 5 - Student Support | B9: ='I-Budget'!D12/'I-Enrollment'!F12 | C9: ='I-Budget'!B12/'I-Enrollment'!F13 | D9: ='I-Budget'!C12/'I-Enrollment'!F10 | E9: ='I-Budget'!E12/'I-Enrollment'!F11 | F9: =AVERAGE(C9:E9) | G9: =B9-F9
A10: Art 7 - Administration | B10: ='I-Budget'!D13/'I-Enrollment'!F12 | C10: ='I-Budget'!B13/'I-Enrollment'!F13 | D10: ='I-Budget'!C13/'I-Enrollment'!F10 | E10: ='I-Budget'!E13/'I-Enrollment'!F11 | F10: =AVERAGE(C10:E10) | G10: =B10-F10
A11: Art 9 - Facilities | B11: ='I-Budget'!D14/'I-Enrollment'!F12 | C11: ='I-Budget'!B14/'I-Enrollment'!F13 | D11: ='I-Budget'!C14/'I-Enrollment'!F10 | E11: ='I-Budget'!E14/'I-Enrollment'!F11 | F11: =AVERAGE(C11:E11) | G11: =B11-F11
A12: TOTAL | B12: =SUM(B6:B11) | F12: =SUM(F6:F11) | G12: =B12-F12
A14: Total Gap (premium x PES enrollment) | B14: =G12*'I-Enrollment'!F12

Sheet C-MSConsol
A1: CALC: Middle School Consolidation
A3: References I-FTE for current staffing, I-Enrollment for student counts, I-Assumptions for targets.
A5: Student Movement
A6: Pownal 6th graders (est.) | B6: =ROUND('C-Enrollment'!B6,0)
A7: Freeport 6th graders (est.) | B7: ='I-Enrollment'!B38-B6
A8: New FMS total (district 7-8) | B8: ='I-Enrollment'!B39+'I-Enrollment'!B40+'I-Enrollment'!B32+'I-Enrollment'!B33
A9: New DCS 6th total (district-wide) | B9: ='I-Enrollment'!B31+'I-Enrollment'!B38
A11: Staffing Impact
A12: Grade Level | B12: Current FTE | C12: Proposed FTE | D12: Change
A13: Grades 7-8 | B13: ='I-FTE'!C22+'I-FTE'!C28 | C13: =B8/'I-Assumptions'!B9 | D13: =C13-B13
A14: Grade 6 | B14: ='I-FTE'!C21+'I-FTE'!C27 | C14: =B9/'I-Assumptions'!B10 | D14: =C14-B14
A15: NET | B15: =B13+B14 | C15: =C13+C14 | D15: =C15-B15
A17: Financial Summary
A18: Net FTE Saved | B18: =-D15
A19: Teacher Savings | B19: =B18*'I-Assumptions'!B8
A20: Extracurricular Savings | B20: ='I-Assumptions'!B11
A21: TOTAL MS CONSOLIDATION SAVINGS | B21: =B19+B20

Sheet C-ECAnalysis
A1: CALC: EC Net Cost Analysis
A3: References I-ECCosts for staff costs and offsets.
A4: NOTE: EC costs are FY28 expenses (begin July 2027), not FY27.
A6: Option 1 Gross Cost | B6: =SUM('I-ECCosts'!D12:'I-ECCosts'!D19)+'I-ECCosts'!D21
A7: Offsets (high -> low net cost) | B7: =SUM('I-ECCosts'!C29:'I-ECCosts'!C31)
A8: Offsets (low -> high net cost) | B8: =SUM('I-ECCosts'!B29:'I-ECCosts'!B31)
A9: Offsets (midpoint) | B9: =AVERAGE(B7,B8)
B11: Low | C11: High | D11: Midpoint
A12: NET EC COST (annual, FY28+) | B12: =B6-B7 | C12: =B6-B8 | D12: =B6-B9

Sheet I-Equity
A1: INPUT: Per-Town Equity & Cost-Sharing Data
A3: Data for analyzing fairness of RSU 5 cost allocation across Pownal, Durham, and Freeport.
A4: Combines enrollment attribution, assessment history, EPS allocation, and cost-sharing formula.
A5: NOTE: FMS and FHS serve multiple towns; per-town estimates use cohort-based attribution.
A6: Sources cited per item. See Sources sheet for full citations.
A8: 1. ENROLLMENT BY TOWN (FY27 Projected) [Fn 1]
A9: SOURCE: FY27 Budget Handbook enrollment table [Fn 1], PES grade data [Fn 1].
A10: PES and DCS are single-town schools. MSS and MLS serve Freeport only.
A11: FMS (6-8) serves Freeport + Pownal. FHS (9-12) serves all three towns.
A12: Secondary attribution is ESTIMATED from cohort sizes at each town's elementary school.
A13: School / Segment | B13: Pownal | C13: Durham | D13: Freeport | E13: Total | F13: Basis
A14: PES (PreK-5) | B14: 105 | C14: 0 | D14: 0 | E14: 105 | F14: PES enrollment, 100% Pownal [Fn 1]
A15: DCS (PreK-8) | B15: 0 | C15: 467 | D15: 0 | E15: 467 | F15: DCS enrollment, 100% Durham [Fn 1]
A16: MSS (PreK-2) | B16: 0 | C16: 0 | D16: 274 | E16: 274 | F16: MSS enrollment, 100% Freeport [Fn 1]
A17: MLS (3-5) | B17: 0 | C17: 0 | D17: 264 | E17: 264 | F17: MLS enrollment, 100% Freeport [Fn 1]
A18: FMS (6-8) - Pownal residents | B18: 45 | C18: 0 | D18: 0 | E18: 45 | F18: Est: PES avg 15/grade × 3 grades [Fn 1]
A19: FMS (6-8) - Freeport residents | B19: 0 | C19: 0 | D19: 261 | E19: 261 | F19: 306 total FMS minus 45 Pownal est.
A20: FHS (9-12) - Pownal residents | B20: 55 | C20: 0 | D20: 0 | E20: 55 | F20: Est: PES avg cohort × 4 grades [Fn 1]
A21: FHS (9-12) - Durham residents | B21: 0 | C21: 225 | D21: 0 | E21: 225 | F21: Est: DCS avg ~56/grade × 4 grades [Fn 1]
A22: FHS (9-12) - Freeport residents | B22: 0 | C22: 0 | D22: 274 | E22: 274 | F22: 554 total FHS minus 55 POW minus 225 DUR
A24: TOTAL STUDENTS - Pownal | B24: =SUM(B14:B22)
A25: TOTAL STUDENTS - Durham | C25: =SUM(C14:C22)
A26: TOTAL STUDENTS - Freeport | D26: =SUM(D14:D22)
A27: TOTAL STUDENTS - All Towns | E27: =SUM(E14:E22)
A29: 2. FY27 PROPOSED ASSESSMENT BY TOWN [Fn 3]
A30: SOURCE: FY27 Budget Handbook, pp.9-10, Budget Impact Summary (02/11/2026) [Fn 3]
A31: RLC = Required Local Contribution (set by Maine DOE via EPS formula).
A32: ALM = Additional Local Monies (allocated by RSU 5 cost-sharing formula).
A33: State Aid = EPS state subsidy (flows directly to RSU, not through town).
A34: Component | B34: Pownal | C34: Durham | D34: Freeport | E34: Total
A35: Required Local Contribution (RLC) | B35: 2257247 | C35: 3910950 | D35: 14173184 | E35: =B35+C35+D35
A36: Additional Local Monies (ALM) | B36: 2190978 | C36: 3724663 | D36: 11473075 | E36: =B36+C36+D36
A37: State Aid | B37: 567180 | C37: 5991564 | D37: 1463889 | E37: =B37+C37+D37
A39: LOCAL TAX ASSESSMENT (RLC + ALM) | B39: =B35+B36 | C39: =C35+C36 | D39: =D35+D36 | E39: =E35+E36
A40: TOTAL FUNDING (Local + State Aid) | B40: =B39+B37 | C40: =C39+C37 | D40: =D39+D37 | E40: =E39+E37
A42: 3. EPS ALLOCATION BY TOWN (FY25-26) [Fn 8]
A43: SOURCE: Maine DOE Warrant Article F, FY25-26 Education Subsidy (09/09/2025) [Fn 8]
A44: EPS allocation = the state's calculated cost of educating each town's students.
A45: Local contribution = minimum local share required to receive state subsidy.
A46: State share = EPS allocation minus local contribution.
B47: Pownal | C47: Durham | D47: Freeport | E47: RSU Total
A48: EPS Total Allocation | B48: 2682829 | C48: 9123077 | D48: 15033673 | E48: =B48+C48+D48
A49: EPS Local Contribution | B49: 2179327 | C49: 3655120 | D49: 13799841 | E49: =B49+C49+D49
A50: EPS State Share | B50: 503502 | C50: 5467957 | D50: 1233833 | E50: =B50+C50+D50
A51: State Share % | B51: =B50/B48 | C51: =C50/C48 | D51: =D50/D48 | E51: =E50/E48
A53: Durham receives 59.9% state share vs. Freeport 8.2% and Pownal 18.8%.
A54: This is because Durham's property values are LOW relative to its student count,
A55: so the state subsidizes more. Freeport is 'property-rich' so gets minimal state aid.
A57: 4. STATE VALUATIONS (FY27 Budget Handbook) [Fn 3]
B58: Pownal | C58: Durham | D58: Freeport | E58: Total
A59: State Valuation | B59: 399866667 | C59: 692816667 | D59: 2510750000 | E59: =B59+C59+D59
A60: % of Total State Valuation | B60: =B59/E59 | C60: =C59/E59 | D60: =D59/E59
A62: 5. RSU 5 COST-SHARING FORMULA [Fn 41][Fn 42]
A63: SOURCE: Portland Press Herald, 10/29/2019: 'RSU 5 looks at new cost-sharing formula.' [Fn 41]
A64: RSU 5 Finance Committee proposed: ALM = 85% state valuation + 15% enrollment. [Fn 41]
A65: Under Title 20-A §1481-A(3), RSU reorganization plans may specify alternate formulas. [Fn 42]
A66: RLC is always allocated by state valuation per the EPS formula (Maine DOE). [Fn 8]
A67: NOTE: The 85/15 formula was proposed in 2019. Actual adopted formula should be confirmed.
B68: Pownal | C68: Durham | D68: Freeport
A69: Enrollment share (students/total) | B69: =B24/E27 | C69: =C25/E27 | D69: =D26/E27
A70: State valuation share | B70: =B59/E59 | C70: =C59/E59 | D70: =D59/E59
A71: Weighted share (85% val + 15% enroll) | B71: =0.85*B70+0.15*B69 | C71: =0.85*C70+0.15*C69 | D71: =0.85*D70+0.15*D69
A72: ACTUAL ALM share (from budget data) | B72: =B36/(B36+C36+D36) | C72: =C36/(B36+C36+D36) | D72: =D36/(B36+C36+D36)
A74: If weighted share ≈ actual ALM share, the 85/15 formula is confirmed.
A75: Any discrepancy may indicate a different formula or adjustment factor.
A77: 6. HISTORICAL POWNAL EDUCATION ASSESSMENT [Fn 9][Fn 4][Fn 43]
A78: SOURCE: Pownal 2025 Annual Report, FY24 audit (year ending June 30, 2024) [Fn 43].
A79: FY26 corroborated: (1) 58.4% RSU × $6.0M levy [Fn 4][Fn 12], (2) consistent with
A80: RSU Q&A total FY26 taxation of $35,600,800 at ~9.85% Pownal share [Fn 44],
A81: (3) FY26 handbook pp.8-9 contains per-town data (PDF image, not text-extractable).
A82: FY27 from Budget Handbook pp.9-10 [Fn 3]. Direct figure from RSU 5 documents.
A83: Fiscal Year | B83: Pownal Assessment | C83: RSU Budget | D83: Pownal % of Budget | E83: Source
A84: FY24 (2023-2024) | B84: 3427607 | C84: 39080569 | D84: =B84/C84 | E84: Audited [Fn 43]
A85: FY25 (2024-2025) | C85: 41612460 | E85: Budget only [Fn 9]
A86: FY26 (2025-2026) | B86: 3506157 | C86: 44455929 | D86: =B86/C86 | E86: Corroborated [Fn 4][Fn 12][Fn 44]
A87: FY27 (2026-2027) | B87: 4448225 | C87: 47357441 | D87: =B87/C87 | E87: Budget Handbook [Fn 3]
A89: FY26 Total RSU Taxation (all towns) | B89: 35600800 | E89: Q&A Budget Doc [Fn 44]
A90: Pownal % of FY26 total taxation | B90: =B86/B89 | E90: Crosscheck: $3.51M / $35.6M = 9.85%
A91: 3-YEAR INCREASE (FY24→FY27) | B91: =B87-B84 | D91: =B91/B84 | E91: Pownal assessment grew 29.8% over 3 years
A92: 1-YEAR INCREASE (FY26→FY27) | B92: =B87-B86 | D92: =B92/B86 | E92: FY26 corroborated via 3 methods [Fn 4][Fn 12][Fn 44]
A93: FY26→FY27 jump driven by Pownal's revaluation feeding into the 85/15 ALM formula.
A94: Pownal's assessed values rose ~20% via revaluation; state valuation followed,
A95: shifting more ALM to Pownal under the valuation-weighted cost-sharing formula.
A97: 7. PROPERTY TAX CONTEXT [Fn 4][Fn 5][Fn 7]
B98: Pownal | C98: Durham | D98: Freeport
A99: Total mil rate (FY26) | B99: 15.3 | C99: 33.58 | D99: 13.85
A100: Assessment ratio | B100: 1 | C100: 0.53 | D100: 1
A101: Taxable valuation | B101: 392398240 | C101: 389646650 | D101: 2613679115
A102: RSU share of tax bill (FY26) | B102: 0.584 | C102: N/A | D102: 0.716
A103: Total tax levy | B103: =B99*B101/1000 | C103: =C99*C101/1000 | D103: =D99*D101/1000
A104: Housing units (est.) | B104: 636 | C104: 1650 | D104: 4100
A106: 8. RLC vs. ALM: WHAT THEY ARE [Fn 8][Fn 42]
A107: RLC (Required Local Contribution):
A108: - Set by Maine DOE under the EPS formula (Title 20-A §15688) [Fn 8]
A109: - Based on each town's STATE VALUATION and the statewide mill rate expectation
A110: - Represents the MINIMUM local investment required to receive state subsidies
A111: - The RSU has NO discretion over RLC amounts; they are state-mandated
A113: ALM (Additional Local Monies):
A114: - Everything the RSU spends ABOVE the EPS-required minimum
A115: - Allocated by RSU 5's cost-sharing formula from the reorganization plan [Fn 42]
...

Sheet I-Withdrawal
A1: INPUT: RSU 5 Withdrawal & Independence Data
A3: Data for modeling Pownal's options if RSU 5 proceeds with PES conversion.
A4: Includes current RSU assessment, independent operating estimates, tuition rates,
A5: EPS allocations, withdrawal process costs, and legal challenge estimates.
A6: Sources cited per item. See Sources sheet for full citations.
A8: 1. POWNAL'S CURRENT RSU 5 POSITION [Fn 3][Fn 8]
A9: Item | B9: Value | C9: Source
A10: Pownal Required Local Contribution (RLC) | B10: 2257247 | C10: FY27 Budget Handbook [Fn 3]
A11: Pownal Additional Local Monies (ALM) | B11: 2190978 | C11: FY27 Budget Handbook [Fn 3]
A12: Pownal LOCAL Tax (RLC + ALM) | B12: =B10+B11 | C12: What Pownal taxpayers actually pay
A13: Pownal State Aid | B13: 567180 | C13: FY27 Budget Handbook [Fn 3]
A14: Pownal Total Contribution (local + state) | B14: 5015405 | C14: RLC + ALM + State Aid [Fn 3]
A15: Pownal Share of RSU 5 Budget | B15: 0.106 | C15: ~10.6% of $47.36M total [Fn 25]
A17: 2. PES CURRENT OPERATING COST [Fn 2]
A18: PES budget detail from I-Budget sheet. These are the costs RSU 5 currently spends on PES.
A19: Budget Article | B19: PES Amount | C19: Source
A20: Art 1 - Regular Instruction | B20: 1196683 | C20: I-Budget [Fn 2]
A21: Art 2 - Special Education | B21: 329115 | C21: I-Budget [Fn 2]
A22: Art 4 - Other Instruction | B22: 13125 | C22: I-Budget [Fn 2]
A23: Art 5 - Student & Staff Support | B23: 219819 | C23: I-Budget [Fn 2]
A24: Art 7 - School Administration | B24: 257979 | C24: I-Budget [Fn 2]
A25: Art 9 - Facilities & Maintenance | B25: 253384 | C25: I-Budget [Fn 2]
A26: PES School-Level Subtotal | B26: =SUM(B20:B25)
A27: PES Enrollment (FY27) | B27: 89 | C27: Budget Handbook [Fn 1]
A28: PES Cost Per Student | B28: =B26/B27
A30: 3. INDEPENDENT OPERATION: ADDITIONAL COSTS [Fn 37][Fn 35]
A31: Costs Pownal would incur beyond PES school-level budget if operating independently.
A32: Estimates derived from comparable Maine independent school units and state averages.
A33: SOURCE: Maine Monitor withdrawal explainer [Fn 37]; DOE tuition rates [Fn 36].
A34: Cost Category | B34: Annual Estimate | C34: Basis / Source
A35: Superintendent (shared or part-time) | B35: 95000 | C35: 50% of ~$190K salary+benefits; comparable AOS arrangements [Fn 37]
A36: Business Manager / Finance | B36: 75000 | C36: Part-time or shared; required for SAU reporting
A37: SpEd Director (shared or contracted) | B37: 65000 | C37: 50% of ~$130K; can share via AOS or contract with neighboring SAU
A38: Central office support (HR, payroll, records) | B38: 55000 | C38: 1 FTE clerical + systems; comparable small-town SAUs
A39: Transportation (K-5 PES routes) | B39: 225000 | C39: 3 routes at $75K/route; current RSU 5 Pownal allocation est.
A40: Transportation (6-12 secondary routes) | B40: 100000 | C40: Est. 1-2 routes Pownal->Freeport, ~12mi each way, $50-75K/route
A41: Secondary tuition (6-12) | B41: =B76*B64 | C41: =total secondary students x state avg rate [Fn 36]
A42: Facilities/maintenance supplement | B42: 50000 | C42: Beyond Art 9 in PES budget; insurance, grounds, capital reserve
A43: Curriculum, technology, assessment | B43: 40000 | C43: Standardized testing, materials, IT support
A44: Board/governance costs | B44: 15000 | C44: Legal counsel retainer, meeting costs, elections
A45: Contingency (5% of above) | B45: =SUM(B35:B44)*0.05 | C45: Calculated below as formula
A46: TOTAL ADDITIONAL COSTS (independence) | B46: =SUM(B35:B45)
A48: 4. AOS SHARED SERVICES SAVINGS ESTIMATE
A49: If Pownal joins an Alternative Organizational Structure (AOS), admin costs are shared.
A50: AOS #94 model: 6 communities share superintendent, SpEd, business office.
A51: Bristol/South Bristol formed 2-town ESC after leaving AOS 93 (2025). [Fn 37]
A52: Shared Service | B52: Estimated Savings | C52: Rationale
A53: Superintendent cost reduction | B53: 47500 | C53: Share with 1-2 other towns -> 50% of $95K
A54: SpEd director cost reduction | B54: 32500 | C54: Share with partner town(s) -> 50% of $65K
A55: Business office cost reduction | B55: 25000 | C55: Share finance/HR -> ~33% of $75K
A56: Transportation coordination | B56: 15000 | C56: Shared routing/dispatch with partner
A57: TOTAL AOS SAVINGS | B57: =SUM(B53:B56)
A59: 5. MAINE SECONDARY TUITION RATES (FY25) [Fn 36]
A60: SOURCE: Maine DOE Public School Secondary Tuition Rates (12/16/2024) [Fn 36]
A61: URL: https://www.maine.gov/doe/funding/reports/tuition
A62: Pownal would tuition secondary students (6-12) to Freeport or other districts.
A63: Item | B63: Rate | C63: Source
A64: State average secondary tuition | B64: 14081 | C64: Maine DOE FY25 [Fn 36]
A65: Freeport/RSU 5 secondary tuition (est.) | B65: 14081 | C65: Capped at state average [Fn 36]
A66: Elementary tuition rate (if needed) | B66: 10500 | C66: State avg elementary rate est. [Fn 36]
A68: 6. POWNAL SECONDARY STUDENTS [Fn 1]
A69: Estimated from PES cohort size. PES has ~15 students/grade historically.
A70: Current 6-12 students entered PES when enrollment was lower (~89-97).
A71: As PES grows (now 105), future steady-state secondary count will be higher.
A72: Matches I-Equity attribution methodology for consistency.
A73: Grade Band | B73: Count | C73: Source
A74: Grades 6-8 (Pownal residents at FMS) | B74: 45 | C74: PES avg ~15/grade x 3 grades [Fn 1]; matches I-Equity
A75: Grades 9-12 (Pownal residents at FHS) | B75: 55 | C75: PES avg ~14/grade x 4 grades [Fn 1]; matches I-Equity
A76: Total secondary students (current) | B76: =SUM(B74:B75)
A77: Steady-state estimate (at PES 105 enrollment) | B77: 123 | C77: 105/6 grades ~ 18/grade; 18x3=54 MS + 18x4=72 HS. Higher than current.
A78: SENSITIVITY: If actual count is 100-123, tuition cost = $1.41M-$1.73M.
A79: This is the largest variable in the independence budget.
A81: 7. WITHDRAWAL PROCESS COSTS [Fn 32][Fn 37]
A82: One-time costs to execute the 22-step withdrawal process under Title 20-A §1466.
A83: Embden (RSU 74) authorized $50K; Phillips authorized $50K. [Fn 37]
A84: Freeport's 2014 RSU 5 withdrawal committee incurred similar costs. [Fn 33]
A85: Item | B85: Estimate | C85: Source
A86: Legal counsel (withdrawal committee) | B86: 35000 | C86: Comparable to Embden/Phillips [Fn 37]
A87: Financial analysis and consulting | B87: 10000 | C87: Budget modeling, EPS projections
A88: Public hearings and elections | B88: 5000 | C88: 2-3 votes required by statute [Fn 32]
A89: Negotiations with RSU 5 Board | B89: 5000 | C89: Committee time, meeting costs
A90: Administrative setup (new SAU) | B90: 15000 | C90: Payroll systems, reporting, accounts
A91: TOTAL PROCESS COSTS | B91: =SUM(B86:B90)
A93: 8. LEGAL CHALLENGE COST ESTIMATES [Fn 30][Fn 39]
A94: If Pownal challenges the 'reconfiguration vs. closure' framing under §1512.
A95: Legal costs for petition to Commissioner or court challenge.
A96: Item | B96: Low | C96: High
A97: Legal counsel for §1512 challenge | B97: 15000 | C97: 50000
A98: Expert witness / education law consultant | B98: 5000 | C98: 20000
A99: Court filing and process costs | B99: 2000 | C99: 10000
A100: Commissioner petition preparation | B100: 3000 | C100: 8000
A101: TOTAL LEGAL CHALLENGE COSTS | B101: =SUM(B97:B100) | C101: =SUM(C97:C100)
A103: 9. EPS ALLOCATION IF INDEPENDENT [Fn 8]
A104: Pownal's EPS allocation would follow the student. Current RSU 5 allocation shown.
A105: Isolated small school adjustment may apply (<200 students). [Fn 8]
A106: State share depends on property valuation vs. enrollment weighting.
A107: Item | B107: Value | C107: Source
A108: Pownal total EPS allocation (FY25-26) | B108: 2682829 | C108: Warrant Article F [Fn 8]
A109: Pownal EPS state share (FY25-26) | B109: 503502 | C109: Warrant Article F [Fn 8]
A110: Isolated small school adjustment (est.) | B110: 75000 | C110: Analyst est.; DOE formula for <200 students [Fn 8]
...

Sheet I-DOEStaffing
A1: INPUT: Maine DOE Historical Staffing (FTE)
A3: SOURCE: Maine DOE NEO Staff Historical Dec 1 Headcount Data [Fn 45]
A4: Dataset: [Fed_Reporting].Reports.StaffHistoricalDec1, SAUOrgId=1449 (RSU 5)
A5: Requested by Mark Dohle (03/04/2026); fulfilled by Maine DOE Data Team (03/09/2026).
A6: DOE Issue #66636. Raw data file: 'MDohle RSU 5 Staff by FTE.xlsx'
A7: FTE = total sum of time staff is employed, as reported Dec 1 each year.
A9: 1. Total FTE by School (All Position Categories)
A10: School | B10: 2016 | C10: 2017 | D10: 2018 | E10: 2019 | F10: 2020 | G10: 2021 | H10: 2022 | I10: 2023 | J10: 2024 | K10: 2025 | L10: 2026
A11: PES (Pownal Elementary) | B11: 26.3 | C11: 33.8 | D11: 29.6 | E11: 28 | F11: 27.7 | G11: 27.3 | H11: 24.5 | I11: 22.5 | J11: 22.9 | K11: 21.5 | L11: 24.2
A12: DCS (Durham Community) | B12: 71.6 | C12: 88 | D12: 84.8 | E12: 92.1 | F12: 94.2 | G12: 93 | H12: 87.6 | I12: 83.5 | J12: 78.4 | K12: 88.8 | L12: 85.7
A13: MSS (Morse Street) | B13: 42.1 | C13: 42.7 | D13: 50.5 | E13: 57.1 | F13: 55.7 | G13: 55.5 | H13: 60.8 | I13: 58.5 | J13: 59.8 | K13: 64.7 | L13: 55
A14: MLS (Mast Landing) | B14: 37 | C14: 48.2 | D14: 46.4 | E14: 50.2 | F14: 55.2 | G14: 46.4 | H14: 50.5 | I14: 49.1 | J14: 45.7 | K14: 53.8 | L14: 50.5
A15: FMS (Freeport Middle) | B15: 63.9 | C15: 71.4 | D15: 75.7 | E15: 74.6 | F15: 71.7 | G15: 58.9 | H15: 67.8 | I15: 69.7 | J15: 62.8 | K15: 64.9 | L15: 66.4
A16: FHS (Freeport High) | B16: 102 | C16: 112.5 | D16: 106 | E16: 124.1 | F16: 123.1 | G16: 112.4 | H16: 100.4 | I16: 100 | J16: 97.4 | K16: 108 | L16: 98.5
A17: District-wide | B17: 103.9 | C17: 123.4 | D17: 111.4 | E17: 125.4 | F17: 115.4 | G17: 118.9 | H17: 119.8 | I17: 129.9 | J17: 116.2 | K17: 144.3 | L17: 139.8
A18: GRAND TOTAL | B18: =SUM(B11:B17) | C18: =SUM(C11:C17) | D18: =SUM(D11:D17) | E18: =SUM(E11:E17) | F18: =SUM(F11:F17) | G18: =SUM(G11:G17) | H18: =SUM(H11:H17) | I18: =SUM(I11:I17) | ... L18: =SUM(L11:L17)
A20: 2. Classroom Teacher FTE by School
A21: DOE 'Classroom Teacher' includes all certified teaching positions (core + specialists).
A22: School | B22: 2016 | C22: 2017 | D22: 2018 | E22: 2019 | F22: 2020 | G22: 2021 | H22: 2022 | I22: 2023 | J22: 2024 | K22: 2025 | L22: 2026
A23: PES | B23: 10.4 | C23: 10.2 | D23: 6.3 | E23: 8.3 | F23: 8.7 | G23: 10.2 | H23: 9.2 | I23: 10.8 | J23: 9.8 | K23: 10.2 | L23: 9.3
A24: DCS | B24: 26 | C24: 31.3 | D24: 25.5 | E24: 30 | F24: 31 | G24: 34 | H24: 33 | I24: 33.5 | J24: 34.5 | K24: 34.5 | L24: 35.5
A25: MSS | B25: 16 | C25: 16.2 | D25: 16.3 | E25: 18.5 | F25: 19.8 | G25: 20.8 | H25: 21.2 | I25: 20.6 | J25: 21.6 | K25: 21.2 | L25: 19.2
A26: MLS | B26: 14.6 | C26: 17.6 | D26: 16.5 | E26: 17.7 | F26: 16.7 | G26: 17.6 | H26: 16.6 | I26: 17.6 | J26: 16.6 | K26: 19.6 | L26: 19.6
A27: FMS | B27: 25.5 | C27: 26.2 | D27: 24.5 | E27: 24.5 | F27: 23.9 | G27: 22.1 | H27: 23.5 | I27: 23.5 | J27: 24 | K27: 23.5 | L27: 23.3
A28: FHS | B28: 37 | C28: 39.1 | D28: 34.5 | E28: 38.6 | F28: 40.7 | G28: 42.2 | H28: 42.2 | I28: 42.7 | J28: 42.7 | K28: 42.6 | L28: 41.7
A30: 3. Special Education Teacher FTE by School
A31: Includes Special Education Teacher + Special Education Consultant positions.
A32: School | B32: 2016 | C32: 2017 | D32: 2018 | E32: 2019 | F32: 2020 | G32: 2021 | H32: 2022 | I32: 2023 | J32: 2024 | K32: 2025 | L32: 2026
A33: PES | B33: 1.8 | C33: 1.8 | D33: 2 | E33: 0.5 | F33: 1 | G33: 1 | H33: 1 | I33: 0 | J33: 0 | K33: 1 | L33: 1.5
A34: DCS | B34: 4 | C34: 5 | D34: 5 | E34: 4.5 | F34: 4 | G34: 4 | H34: 4 | I34: 4 | J34: 4 | K34: 5 | L34: 6.1
A35: MSS | B35: 2 | C35: 2 | D35: 2 | E35: 3 | F35: 3 | G35: 3 | H35: 3 | I35: 4.1 | J35: 4.1 | K35: 6 | L35: 4.9
A36: MLS | B36: 2 | C36: 2 | D36: 3 | E36: 2 | F36: 3 | G36: 3 | H36: 3 | I36: 3 | J36: 4 | K36: 4 | L36: 4.5
A37: FMS | B37: 4 | C37: 4 | D37: 4 | E37: 4 | F37: 3 | G37: 4 | H37: 4 | I37: 4 | J37: 4 | K37: 4 | L37: 4.5
A38: FHS | B38: 5 | C38: 6 | D38: 5 | E38: 5 | F38: 5 | G38: 5 | H38: 4 | I38: 4 | J38: 4 | K38: 5 | L38: 4.5
A40: 4. Ed Tech FTE (I + II + III + Library/Media) by School
A41: Includes Ed Tech I, Ed Tech II, Ed Tech II - Library/Media, Ed Tech III.
A42: School | B42: 2016 | C42: 2017 | D42: 2018 | E42: 2019 | F42: 2020 | G42: 2021 | H42: 2022 | I42: 2023 | J42: 2024 | K42: 2025 | L42: 2026
A43: PES | B43: 6.4 | C43: 7.4 | D43: 5.7 | E43: 4.7 | F43: 4.2 | G43: 4.5 | H43: 3.1 | I43: 2.1 | J43: 5.1 | K43: 3.1 | L43: 4
A44: DCS | B44: 10 | C44: 11 | D44: 15 | E44: 13 | F44: 14 | G44: 14.5 | H44: 16 | I44: 14 | J44: 12 | K44: 13 | L44: 13.5
A45: MSS | B45: 8 | C45: 8 | D45: 13.4 | E45: 12.4 | F45: 12.5 | G45: 14 | H45: 15 | I45: 14.6 | J45: 16.6 | K45: 15 | L45: 12
A46: MLS | B46: 6.1 | C46: 5.6 | D46: 4.5 | E46: 3 | F46: 7 | G46: 6 | H46: 8 | I46: 6 | J46: 7 | K46: 11 | L46: 7
A47: FMS | B47: 8.5 | C47: 10.5 | D47: 13.5 | E47: 12.5 | F47: 11.5 | G47: 9.1 | H47: 11.2 | I47: 16.2 | J47: 14.2 | K47: 10.2 | L47: 11.1
A48: FHS | B48: 10 | C48: 11.3 | D48: 9 | E48: 8 | F48: 12 | G48: 10 | H48: 10 | I48: 8 | J48: 5.5 | K48: 9 | L48: 6

Sheet I-Enrollment
A1: INPUT: Enrollment Data
A3: SOURCE: FY27 Budget Handbook, RSU 5 Superintendent's Office, pp.3-4 (02/11/2026) [Fn 1]
A4: "Projected Enrollment 2026-2027" table and Teacher/Class Size table.
A5: URL: https://resources.finalsite.net/images/v1770852522/rsu5org/ytm49nnwpbrzi4oiwg4i/FY27BUDGETHANDBOOK02112026.pdf
A6: All enrollment figures are October 1 counts as reported by RSU 5.
A8: 1A. Historical Enrollment by School
A9: School | B9: Grades | C9: Oct 2023 | D9: Oct 2024 | E9: Oct 2025 | F9: Oct 2026P
A10: MSS (Morse Street) | B10: PreK-2 | C10: 316 | D10: 288 | E10: 275 | F10: 274
A11: MLS (Mast Landing) | B11: 3-5 | C11: 281 | D11: 266 | E11: 282 | F11: 264
A12: PES (Pownal Elementary) | B12: PreK-5 | C12: 89 | D12: 97 | E12: 98 | F12: 105
A13: DCS (Durham Community) | B13: PreK-8 | C13: 473 | D13: 466 | E13: 453 | F13: 467
A14: FMS (Freeport Middle) | B14: 6-8 | C14: 293 | D14: 288 | E14: 286 | F14: 306
A15: FHS (Freeport High) | B15: 9-12 | C15: 632 | D15: 592 | E15: 577 | F15: 554
A17: 1B. PES Grade-Level Enrollment (for cohort estimation)
A18: Source: same Budget Handbook, Teacher/Class Size table, p.4
A19: Grade | B19: Students | C19: Teachers
A20: PreK | B20: 16 | C20: 0.5
A21: K | B21: 14 | C21: 1
A22: 1 | B22: 14 | C22: 1
A23: 2 | B23: 13 | C23: 1
A24: 3 | B24: 17 | C24: 1
A25: 4 | B25: 13 | C25: 1
A26: 5 | B26: 18 | C26: 1
A28: 1C. DCS Middle-Grade Enrollment
A29: Source: same Budget Handbook, Teacher/Class Size table
A30: Grade | B30: Students
A31: Grade 6 | B31: 41
A32: Grade 7 | B32: 46
A33: Grade 8 | B33: 54
A35: 1D. FMS Grade-Level Enrollment
A36: Source: same Budget Handbook. FMS 6th total includes Pownal + Freeport students.
A37: Grade | B37: Students
A38: Grade 6 (all towns) | B38: 116
A39: Grade 7 | B39: 95
A40: Grade 8 | B40: 95

Sheet I-Budget
A1: INPUT: FY27 Proposed Budget by Cost Center
A3: SOURCE: FY27 Superintendent's Proposed Budget Articles, 89-page line-item detail (02/11/2026) [Fn 2]
A4: URL: https://resources.finalsite.net/images/v1770852540/rsu5org/spzuwjskm8vh3t9bjck8/2026-2027SuperintendentsRecommendedBudgetArticlesforWebsite02112026.pdf
A5: Each cell value is the total for that school x article combination as reported in the budget articles.
A6: SYS = system-wide allocation; K8 = K-8 allocation; 912 = 9-12 allocation; CTRL = central office.
A8: Article | B8: DCS | C8: MSS | D8: PES | E8: MLS | F8: FMS | G8: FHS | H8: SYS | I8: K8 | J8: 912 | K8: CTRL
A9: Art 1 - Regular Instruction | B9: 4611862 | C9: 2506278 | D9: 1196683 | E9: 2338114 | F9: 3201928 | G9: 5310140 | H9: 0 | I9: 420852 | J9: 287336 | K9: 0
A10: Art 2 - Special Education | B10: 1553029 | C10: 1037964 | D10: 329115 | E10: 971107 | F10: 1062320 | G10: 1013463 | H10: 836683 | I10: 347140 | J10: 359601 | K10: 0
A11: Art 4 - Other Instruction | B11: 90140 | C11: 7710 | D11: 13125 | E11: 12626 | F11: 277908 | G11: 769494 | H11: 0 | I11: 1536 | J11: 0 | K11: 0
A12: Art 5 - Student & Staff Support | B12: 581386 | C12: 400046 | D12: 219819 | E12: 363844 | F12: 490321 | G12: 1061829 | H12: 1523668 | I12: 249421 | J12: 16032 | K12: 0
A13: Art 7 - School Administration | B13: 515193 | C13: 421185 | D13: 257979 | E13: 400206 | F13: 462558 | G13: 580903 | H13: 0 | I13: 0 | J13: 0 | K13: 0
A14: Art 9 - Facilities & Maintenance | B14: 683965 | C14: 569640 | D14: 253384 | E14: 482373 | F14: 641780 | G14: 1745609 | H14: 1564602 | I14: 0 | J14: 0 | K14: 52424
A16: System-Only Articles (not allocated to individual schools)
A17: SOURCE: Same 89-page budget articles document [Fn 2].
A18: These articles are district-wide and have no school-level breakdown.
A19: Article | B19: Amount
A20: Art 3 - CTE | B20: 337282
A21: Art 6 - System Administration | B21: 1308008
A22: Art 8 - Transportation | B22: 2388457
A23: Art 10 - Debt Service | B23: 1071577
A24: Art 11 - All Other | B24: 69796
A26: Budget Totals
A27: FY27 total: Revised Budget Handbook 02/11/2026. Articles 1-11 + Adult Ed = $47,357,441 [Fn 25]
A28: URL: https://www.rsu5.org/fs/resource-manager/view/78dce71e-a8e6-4435-b33f-9746e8541a3a
A29: FY26 adopted: $44,455,929, approved by voters 06/10/2025 (817 Yes, 494 No) [Fn 9]
A30: Item | B30: Amount
A31: Adult Education | B31: 88000
A32: FY26 Adopted Budget | B32: 44455929

Sheet I-Revenue
A1: INPUT: Revenue by Town (FY27 Proposed)
A3: SOURCE: FY27 Budget Handbook, RSU 5, Budget Impact Summary pp.9-10 (02/11/2026) [Fn 3]
A4: URL: https://resources.finalsite.net/images/v1770852522/rsu5org/ytm49nnwpbrzi4oiwg4i/FY27BUDGETHANDBOOK02112026.pdf
A5: Revenue components as reported on the cost-sharing summary page.
A6: Shared Revenue total from same page; allocated by ALM percentage.
A8: Component | B8: Pownal | C8: Durham | D8: Freeport
A9: Required Local Contribution (RLC) | B9: 2257247.3 | C9: 3910950.1 | D9: 14173184
A10: Additional Local Monies (ALM) | B10: 2190978.3 | C10: 3724663.2 | D10: 11473075
A11: State Aid | B11: 567179.79 | C11: 5991563.9 | D11: 1463888.5
A12: Non-Shared Debt Service | B12: 0 | C12: 117175.57 | D12: 0
A14: Total Shared Revenue | B14: 1431699.1
A15: Shared revenue is allocated by each town's ALM percentage (computed on Calc sheets).

Sheet I-Tax
A1: INPUT: Tax Rates & Property Valuations
A3: POWNAL
A4: SOURCE: Pownal FY26 Real Estate Tax Commitment Book, committed 07/29/2025 [Fn 4]
A5: Tax rate: $15.300/thousand. Town of Pownal Assessor, https://www.pownalmaine.org/
A6: Tax breakdown: RSU 58.4%, County 3.3%, Town 38.3% [Fn 12].
A7: State valuation: $399,866,667 [Fn 3].
A8: Item | B8: Value | C8: Source Detail
A9: Total Mil Rate | B9: 15.3 | C9: Commitment Book [Fn 4]
A10: RSU Share of Tax | B10: 0.584 | C10: Municipal records [Fn 12]
A11: County Share of Tax | B11: 0.033 | C11: Municipal records [Fn 12]
A12: Town Share of Tax | B12: 0.383 | C12: Municipal records [Fn 12]
A13: Taxable Valuation | B13: 392398240 | C13: Commitment Book final total [Fn 4]
A14: State Valuation | B14: 399866667 | C14: Budget Handbook p.10 [Fn 3]
A16: FREEPORT
A17: SOURCE: Freeport FY26 tax rate $13.85/thousand at 100% assessment ratio [Fn 5]
A18: Freeport Assessor, committed 09/15/2025. https://www.freeportmaine.com/158/Assessor
A19: Component breakdown from FY25 Budget Presentation (FY26 detail not yet public) [Fn 6]
A20: Valuations from FY27 Budget Handbook [Fn 3].
A21: Item | B21: Value | C21: Source Detail
A22: Total Mil Rate | B22: 13.85 | C22: Freeport Assessor [Fn 5]
A23: RSU Share (FY25 proxy) | B23: 0.716 | C23: FY25 Budget Presentation [Fn 6]
A24: Taxable Valuation | B24: 2613679115 | C24: Budget Handbook [Fn 3]
A25: State Valuation | B25: 2510750000 | C25: Budget Handbook [Fn 3]
A27: DURHAM
A28: SOURCE: Durham FY26 tax rate $33.58/thousand, ~53% assessment ratio [Fn 7]
A29: Durham Assessor, committed 08/12/2025. https://durhammaine.gov/pages/assessing
A30: Note: computed assessment ratio (taxable/state val) = 56.2%, vs. Assessor's stated ~53%.
A31: Valuations from FY27 Budget Handbook [Fn 3].
A32: Item | B32: Value | C32: Source Detail
A33: Total Mil Rate | B33: 33.58 | C33: Durham Assessor [Fn 7]
A34: Taxable Valuation | B34: 389646650 | C34: Budget Handbook [Fn 3]
A35: State Valuation | B35: 692816667 | C35: Budget Handbook [Fn 3]
A37: MAINE EPS FUNDING (FY25-26)
A38: SOURCE: Maine DOE FY25-26 Warrant Article F: Education Subsidy Information (09/09/2025) [Fn 8]
A39: URL: https://www.maine.gov/doe/sites/maine.gov.doe/files/inline-files/School%20Finance%20-%20FY25-26%20Warrant%20Article%20F%20Education%20Subsidy%20Information%20for%20Property%20Tax%20Bill%20-%209.9.2025.pdf
A40: Town | B40: Total EPS Allocation | C40: Local Share | D40: EPS Mill Rate | E40: State Share
A41: Pownal | B41: 2682829 | C41: 2179326.7 | D41: 6.1 | E41: 503502.31
A42: Durham | B42: 9123076.7 | C42: 3655120 | D42: 6.1 | E42: 5467956.7
A43: Freeport | B43: 15033673 | C43: 13799841 | D43: 5.95 | E43: 1233832.6

Sheet I-ECCosts
A1: INPUT: Early Childhood (CDS Transition) Costs
A3: SOURCE: RSU 5 Service Model Options PK3, presented at Dec 18, 2025 Task Force meeting [Fn 19]
A4: URL: https://www.rsu5.org/fs/resource-manager/view/da1426f4-8cc1-4b09-bd89-477da9c623ed
A5: Task Force membership and schedule: https://www.rsu5.org/quick-links/early-childhood-planning-cds [Fn 18]
A6: EC mandate: Portland Press Herald, 10/02/2025 [Fn 17]. Deadline: July 1, 2028 statewide;
A7: RSU 5 committed to Cohort 3 (July 2027) per Superintendent's 02/11/2026 presentation [Fn 10].
A8: NOTE: EC costs are FY28 expenses (begin July 2027). They do NOT appear in the FY27 budget.
A10: Option 1: School-Based with SpEd Classroom (Task Force Recommended)
A11: Position | B11: Unit Cost | C11: Count | D11: Total
A12: ECSE Coordinator (Asst. Director) | B12: 176000 | C12: 1 | D12: 176000
A13: Office Support / Transport Coord. | B13: 105000 | C13: 1 | D13: 105000
A14: SpEd Teacher (282B) | B14: 144000 | C14: 1 | D14: 144000
A15: Ed Techs | B15: 53000 | C15: 3 | D15: 159000
A16: Speech-Language Pathologist | B16: 177000 | C16: 1 | D16: 177000
A17: Social Worker | B17: 177000 | C17: 1 | D17: 177000
A18: Driver Hours | B18: 13000 | C18: 1 | D18: 13000
A19: Contractors (Psych, TOD, TVI, etc.) | B19: 177000 | C19: 1 | D19: 177000
A21: Equipment (van, tech, assessments) | D21: 61644
A23: Estimated State/Federal Offsets
A24: CDS budget transfer: State transfers existing CDS funding per child served [Fn 17].
A25: IDEA Part B: Federal special ed dollars follow children to districts (federal guidelines).
A26: EPS PreK subsidy: Maine DOE Public Pre-K Guidebook (01/21/2025) [Fn 15].
A27: NOTE: These are estimated ranges. Actual amounts depend on enrollment and state allocations.
A28: Offset Source | B28: Low Estimate | C28: High Estimate
A29: CDS budget transfer to districts [Fn 17] | B29: 200000 | C29: 400000
A30: IDEA Part B (federal 3-5 funding) | B30: 100000 | C30: 150000
A31: EPS subsidy for PreK students [Fn 15] | B31: 50000 | C31: 100000

Sheet I-Assumptions
A1: INPUT: Analyst Assumptions & Estimates
A3: These are assumptions used in scenario modeling. They are NOT from official RSU 5 documents.
A4: Each assumption is sourced where possible; otherwise marked as analyst estimate.
A5: Users should adjust these values to test sensitivity of results.
A7: Assumption | B7: Value | C7: Source / Rationale
A8: Cost per FTE (salary + benefits) | B8: 107700 | C8: Derived from budget articles average compensation [Fn 2]
A9: 7-8 target class size | B9: 22 | C9: RSU 5 current middle school practice [Fn 1]
A10: 6th grade target class size | B10: 20 | C10: Upper elementary norm; lower than MS to reflect transition year
A11: Extracurricular consolidation savings | B11: 40000 | C11: Analyst estimate: consolidated athletics/activities for 7-8
A12: Bus route cost (standard, annual) | B12: 75000 | C12: Analyst estimate: driver + fuel + maintenance per route
A13: Freeport 6th to DCS routes needed | B13: 2 | C13: ~101 students, ~9 miles; 2 bus routes required
A14: Pownal K-6 to DCS routes needed (Path B) | B14: 3 | C14: ~104 students from rural Pownal, ~11 miles
A15: Freeport PreK to PES routes needed (Path B) | B15: 3 | C15: ~64 students, specialized vehicles, ~13 miles
A16: Durham PreK to PES routes needed (Path B) | B16: 2 | C16: ~48 students, specialized vehicles, ~11 miles
A17: PES partial conversion cost (Path B) | B17: 425000 | C17: K-5 to EC; bathrooms, playground, plumbing [Fn 21][Fn 24]
A18: PES full conversion multiplier | B18: 1.75 | C18: Full EC center requires most rooms converted vs. partial
A19: Conversion amortization period (years) | B19: 10 | C19: Standard capital project amortization
... A27: Birth rate per 1,000 [Fn 14] | B27: 9.5 | C27: Cumberland/Androscoggin County avg, CDC WONDER

Sheet I-FY27Reductions
A1: INPUT: FY27 Proposed Budget Reductions
A3: SOURCE: FY27 Budget Handbook, pp.6-7 Expenditure/Reductions Summary (02/11/2026) [Fn 25]
A4: URL: https://resources.finalsite.net/images/v1770852522/rsu5org/ytm49nnwpbrzi4oiwg4i/FY27BUDGETHANDBOOK02112026.pdf
A5: These reductions are ALREADY INCLUDED in the $47,357,441 proposed budget.
A6: The initial request was $49,148,089 (10.55% increase). Reductions bring it to 6.53%.
A7: Rating: M=Maintenance, N=Necessary, R=Recommended, T1=Tier 1 Cut, T2=Tier 2 Cut.
A9: Budget Timeline
A10: Board Adopts FY27 Budget: March 25, 2026
A11: Annual Budget Meeting (voter vote): May 13, 2026
A12: Budget Validation Referendum: June 19, 2026
A13: EC Cohort 3 deadline: July 1, 2027 (FY28, not FY27)
A15: Initial Request vs. Proposed
A16: Item | B16: Amount
A17: Initial request increase (10.55%) | B17: 4692160
A18: Total reductions applied | B18: -1715649
A19: Redirected to reserves | B19: -75000
A20: NET proposed increase (6.53%) | B20: 2901512
A22: Tier 1 Reductions (Staff Positions)
A23: Tier | B23: Description | C23: School | D23: Initial | E23: Reduction | F23: Proposed
A24: T1 | B24: 1 FTE Grade 1 Educator | C24: DCS | D24: 0 | E24: -107700 | F24: -107700
A25: T1 | B25: 1 FTE Grade 2 Educator | C25: MSS | D25: 0 | E25: -107700 | F25: -107700
A26: T1 | B26: 1 FTE Grade 3 Educator | C26: MLS | D26: 0 | E26: -107700 | F26: -107700
A27: T1 | B27: .25 FTE Math RTI Educator | C27: FMS | D27: 0 | E27: -26925 | F27: -26925
A28: T1 | B28: 16.25hr Office Support | C28: FMS | D28: 0 | E28: -26756 | F28: -26756
A29: T1 | B29: .5 FTE ELA Educator | C29: FMS | D29: 0 | E29: -53850 | F29: -53850
A30: T1 | B30: .25 FTE ELA Educator | C30: FMS | D30: 0 | E30: -26925 | F30: -26925
A31: T1 | B31: 1 FTE French Educator | C31: FMS | D31: 0 | E31: -107700 | F31: -107700
A32: T1 | B32: 1 FTE Math Educator | C32: FHS | D32: 0 | E32: -107700 | F32: -107700
A33: T1 | B33: Printing Clerk | C33: FHS | D33: 0 | E33: -21738 | F33: -21738
A34: T1 | B34: 1 FTE Latin Educator | C34: FHS | D34: 0 | E34: -107700 | F34: -107700
A35: T1 | B35: .5 FTE Community Outreach Coord. | C35: FHS | D35: 0 | E35: -57059 | F35: -57059
A36: T1 | B36: 1 FTE ESOL Educator | C36: DW | D36: 0 | E36: -107700 | F36: -107700
A38: Tier 2 Reductions (Support Positions)
A39: Tier | B39: Description | C39: School | D39: Initial | E39: Reduction | F39: Proposed
A40: T2 | B40: 32.5hr Ed Tech (Bench Sub) | C40: DCS | D40: 0 | E40: -52600 | F40: -52600
A41: T2 | B41: 32.5hr Ed Tech (RTI) | C41: MSS | D41: 0 | E41: -52600 | F41: -52600
A42: T2 | B42: 32.5hr Ed Tech (RTI) | C42: MLS | D42: 0 | E42: -52600 | F42: -52600
A43: T2 | B43: 32.5hr Ed Tech (General Ed) | C43: FMS | D43: 0 | E43: -52600 | F43: -52600
A44: T2 | B44: 32.5hr Ed Tech (General Ed) | C44: FMS | D44: 0 | E44: -52600 | F44: -52600
A45: T2 | B45: 1 Instructional Strategist (K-5) | C45: DW | D45: 0 | E45: -107700 | F45: -107700
A46: T2 | B46: School Nutrition | C46: DW | D46: 0 | E46: -69796 | F46: -69796
A48: Other Reductions
A49: Tier | B49: Description | C49: School | D49: Initial | E49: Reduction | F49: Proposed
A50: R/T1/T2 | B50: Technology (software, devices, AV) | C50: DW | D50: 336758 | E50: -250000 | F50: 86758
A51: R/T1 | B51: Facilities Maintenance (paint/carpet) | C51: DW | D51: 116000 | E51: -58000 | F51: 58000
A52: R | B52: Facilities Study | C52: DW | D52: 75000 | E52: -75000 | F52: 0

Sheet I-CostGrowth
A1: INPUT: 10-Year Adopted Budget History
A3: SOURCE: FY27 Budget Handbook, p.5 '10 Year Adopted Budget History' (02/11/2026) [Fn 25]
A4: URL: https://resources.finalsite.net/images/v1770852522/rsu5org/ytm49nnwpbrzi4oiwg4i/FY27BUDGETHANDBOOK02112026.pdf
A5: Used to project FY28 cost growth from FY27 adopted baseline.
A7: FY | B7: Adopted Budget | C7: $ Increase | D7: % Increase
A8: FY17 | B8: 31008672 | C8: 1518469 | D8: 0.0515
A9: FY18 | B9: 32310685 | C9: 1302013 | D9: 0.042
A10: FY19 | B10: 33058025 | C10: 747340 | D10: 0.0231
A11: FY20 | B11: 34192295 | C11: 1134270 | D11: 0.0343
A12: FY21 | B12: 34984700 | C12: 792405 | D12: 0.0232
A13: FY22 | B13: 35714863 | C13: 730163 | D13: 0.0209
A14: FY23 | B14: 37223151 | C14: 1508288 | D14: 0.0422
A15: FY24 | B15: 39080569 | C15: 1857418 | D15: 0.0499
A16: FY25 | B16: 41612460 | C16: 2531891 | D16: 0.0648
A17: FY26 | B17: 44455929 | C17: 2843469 | D17: 0.0683

Sheet I-FTE
A1: INPUT: Teacher FTE by School & Grade Band
A3: SOURCE: FY27 Budget Handbook, p.4 Teacher/Class Size table (02/11/2026) [Fn 1]
A4: NOTE: These are PROPOSED FY27 staffing levels. T1/T2 cuts are already reflected.
A5: FTE figures include classroom teachers only (not aides, specialists, or admin).
A6: Grade-band detail for FMS and DCS drives the middle school consolidation model.
A8: School-Level Teacher FTE (Proposed FY27)
A9: School | B9: Grades | C9: Enrollment | D9: Teacher FTE | E9: Notes
A10: PES (Pownal Elementary) | B10: PreK-5 | C10: 105 | D10: 6.5 | E10: Verified from grade-level data (I-Enrollment 1B)
A11: DCS (Durham Community) | B11: PreK-8 | C11: 467 | D11: 26.5 | E11: Includes PreK through 8; T1: -1 Grade 1 educator
A12: MSS (Morse Street) | B12: PreK-2 | C12: 274 | D12: 14 | E12: T1: -1 Grade 2 educator; T2: -1 Ed Tech
A13: MLS (Mast Landing) | B13: 3-5 | C13: 264 | D13: 14 | E13: T1: -1 Grade 3 educator; T2: -1 Ed Tech
A14: FMS (Freeport Middle) | B14: 6-8 | C14: 306 | D14: 15.48 | E14: T1: -2.0 FTE (Math, ELA, French); T2: -2 Ed Techs
A15: FHS (Freeport High) | B15: 9-12 | C15: 554 | D15: 38 | E15: Estimated from Art 1 budget; T1: -2.5 FTE
A17: Grade-Band Detail: DCS (for consolidation model)
A18: Grade Band | B18: Students | C18: Teacher FTE | D18: Notes
A19: DCS PreK | B19: 48 | C19: 2.5 | D19: 3 sections, ~16/class
A20: DCS K-5 | B20: 278 | C20: 16 | D20: Post T1 cut: 1 Grade 1 educator removed
A21: DCS Grade 6 | B21: 41 | C21: 2 | D21: 2 sections, ~20.5/class
A22: DCS Grades 7-8 | B22: 100 | C22: 6 | D22: Grades 7 (46) + 8 (54)
A23: DCS Check Total | C23: =C19+C20+C21+C22 | D23: Should equal 26.5
A25: Grade-Band Detail: FMS (for consolidation model)
A26: Grade Band | B26: Students | C26: Teacher FTE | D26: Notes
A27: FMS Grade 6 | B27: 116 | C27: 5.16 | D27: Pownal + Freeport 6th graders
A28: FMS Grades 7-8 | B28: 190 | C28: 10.32 | D28: Post T1: -0.25 Math RTI, -0.75 ELA, -1.0 French
A29: FMS Check Total | C29: =C27+C28 | D29: Should be close to 15.5
A31: Scenario 2 (Path B) FTE Model
A32: Source: District-wide restructuring plan from Superintendent's 02/11/2026 presentation [Fn 10].
A33: Shows how each school's role and FTE would change under full Scenario 2.
A34: School | B34: Current FTE | C34: Scenario 2 FTE | D34: Change | E34: Scenario 2 Role
A35: PES | B35: 6.5 | C35: 5 | D35: =C35-B35 | E35: EC center (district PreK)
A36: DCS | B36: 26.5 | C36: 23 | D36: =C36-B36 | E36: K-6 Durham + Pownal
A37: MSS | B37: 14 | C37: 16 | D37: =C37-B37 | E37: K-3 Freeport
A38: MLS | B38: 14 | C38: 15 | D38: =C38-B38 | E38: 4-6 Freeport
A39: FMS | B39: 15.5 | C39: 13 | D39: =C39-B39 | E39: 7-8 district-wide
A41: TOTAL | B41: =SUM(B35:B39) | C41: =SUM(C35:C39) | D41: =C41-B41
A42: Net FTE Saved (Scenario 2) | B42: =-D41

Sheet Sources
A1: Source Citations
A3: Every input cell in this workbook references one of these footnoted sources.
A5: [Fn 1] | B5: FY27 Budget Handbook, RSU 5 Superintendent's Office, pp.3-4 (02/11/2026). "Projected Enrollment 2026-2027" and Teacher/Class Size table.
A6: [Fn 2] | B6: FY27 Superintendent's Proposed Budget Articles, 89-page line-item detail (02/11/2026). URL: https://resources.finalsite.net/images/v1770852540/rsu5org/spzuwjskm8vh3t9bjck8/2026-2027SuperintendentsRecommendedBudgetArticlesforWebsite02112026.pdf
A7: [Fn 3] | B7: FY27 Budget Handbook, RSU 5, Budget Impact Summary pp.9-10 (02/11/2026). URL: https://resources.finalsite.net/images/v1770852522/rsu5org/ytm49nnwpbrzi4oiwg4i/FY27BUDGETHANDBOOK02112026.pdf
A8: [Fn 4] | B8: Pownal FY26 Real Estate Tax Commitment Book, committed 07/29/2025, rate $15.300/thousand. Source: Town of Pownal Assessor, https://www.pownalmaine.org/
A9: [Fn 5] | B9: Freeport FY26 tax rate $13.85/thousand at 100% assessment ratio, committed 09/15/2025. Source: Freeport Assessor, https://www.freeportmaine.com/158/Assessor
A10: [Fn 6] | B10: Freeport FY25 Budget Presentation, Proposed Tax Changes table. URL: https://www.freeportmaine.com/DocumentCenter/View/2711/FY-25-Budget-Presentation
A11: [Fn 7] | B11: Durham FY26 tax rate $33.58/thousand at ~53% assessment ratio, committed 08/12/2025. Source: Durham Assessor, https://durhammaine.gov/pages/assessing
A12: [Fn 8] | B12: Maine DOE FY25-26 Warrant Article F: Education Subsidy Information for Property Tax Bill (09/09/2025). URL: https://www.maine.gov/doe/sites/maine.gov.doe/files/inline-files/School%20Finance%20-%20FY25-26%20Warrant%20Article%20F%20Education%20Subsidy%20Information%20for%20Property%20Tax%20Bill%20-%209.9.2025.pdf
A13: [Fn 9] | B13: FY26 Adopted Budget, RSU 5, $44,455,929 total. Approved by voters 06/10/2025 (817 Yes, 494 No). Source: https://www.rsu5.org/budget/fy26
A14: [Fn 10] | B14: RSU 5 Planning for the Future presentation (02/11/2026). URL: https://resources.finalsite.net/images/v1770852531/rsu5org/vfrsu75oj4ebaxvsbcwc/PlanningfortheFutureofRSU5.pdf
A15: [Fn 12] | B15: Pownal tax breakdown (RSU 58.4%, County 3.3%, Town 38.3%) from Pownal municipal records, FY26.
A16: [Fn 13] | B16: Census/ACS population estimates: Pownal 1,590; Durham 4,339; Freeport 8,771. Sources: censusreporter.org, maine-demographics.com (2023 est.)
... A47: [Fn 45] | B47: Maine DOE NEO Staff Historical Data (Dec 1, 2015-2025). Dataset: [Fed_Reporting].Reports.StaffHistoricalDec1, SAUOrgId=1449. Requested by Mark Dohle (03/04/2026), fulfilled by Maine DOE Data Team (Trevor R. Burns, 03/09/2026). DOE Helpdesk Issue #66636. File: 'MDohle RSU 5 Staff by FTE.xlsx'. Public use; FTE headcounts reported as of December 1 each year.
